Workbook

Sheet À lire
A1: Export du catalogue PrestaShop (abcterroirs.com) avec les références LMB
A2: Extrait le 16/10/2026 : 464 produits du site (344 actifs, 120 désactivés), rapprochés de l'extraction LMB « ETIQUETTES_PRIX_BD_au_141026 » puis vérifiés dans le catalogue LMB en ligne (archives comprises) le 19/10/2026.
A4: Colonne « Statut réf. LMB » (le décompte ci-dessous se met à jour tout seul) :
A5: Confirmée | B5: =COUNTIF(Produits!C:C,A5) -> 88
A6: Corrigée | B6: =COUNTIF(Produits!C:C,A6) -> 81
A7: Ajoutée | B7: =COUNTIF(Produits!C:C,A7) -> 251
A8: Ajoutée, à vérifier | B8: =COUNTIF(Produits!C:C,A8) -> 5
A9: Corrigée, à vérifier | B9: =COUNTIF(Produits!C:C,A9) -> 1
A10: À vérifier | B10: =COUNTIF(Produits!C:C,A10) -> 1
A11: Introuvable dans LMB | B11: =COUNTIF(Produits!C:C,A11) -> 4
A12: Total | B12: =SUM(B5:B11) -> 431
A14: Comment les références ont été trouvées
A15: - Chaque produit a été comparé aux articles LMB par le nom (actuel et ancien nom du site), le prix TTC et la contenance, puis vérifié à la main.
A16: - Vert : référence sûre. Jaune : référence probable ou plusieurs possibles, voir la colonne Remarque. Rouge : aucun article LMB ne correspond (produit plus vendu, ou absent de LMB).
A17: - Colonne « Ancienne réf. (site) » : ce qui était renseigné sur PrestaShop, gardé pour mémoire. Les anciennes réf. sans « A- » ne sont pas des références LMB.
A18: - Plusieurs produits du site partagent parfois la même réf. LMB : LMB regroupe certains parfums ou formats (ex. Nona 20 cl, Ginger & Ginger, rhums arrangés 20 cl, places de dégustation).
A20: Autres onglets et fichiers
A21: - Onglet « Descriptions HTML » : descriptions avec la mise en forme du site. Fichier produits-prestashop.csv : même contenu que « Produits », pour un import.
A22: - Aucun code-barres (EAN) ni prix d'achat n'est renseigné sur le site. Prix TTC = prix HT × (1 + TVA), calculé dans le fichier.
A23: - Rien n'a été modifié sur le site ni dans LMB : les références du site PrestaShop restent à mettre à jour (je peux le faire sur demande).

Sheet Produits
A1: Référence LMB | B1: Ancienne réf. (site) | C1: Statut réf. LMB | D1: Libellé LMB | E1: Prix TTC LMB (€) | F1: Remarque | G1: Désignation | H1: Description courte | I1: Description longue | J1: Prix de vente HT (€) | K1: TVA | L1: Prix de vente TTC (€) | M1: Catégorie (site) | N1: Caractéristiques | O1: Poids (kg) | P1: Actif sur le site | Q1: ID PrestaShop | R1: Lien produit
A2: A-01002 | B2: A-01002 | C2: Confirmée | D2: GWENRANN LK CHOCOLAT LAIT ou NOIR FDS BIO 85g | E2: 6.9 | G2: Palets chocolat et fleur de sel bio – Gwenrann 85 g | H2: SUPERBE CHOCOLAT NOIR OU LAIT AVEC INCLUSION DE FLEUR DE SEL, LE COMPAGNON IDEAL POUR UNE PAUSE CAFÉ ! MERCI LAURENT POUR CETTE CREATION QUI EST UN DES SUCCES DU MAGASIN !! | I2: Gwenrann, Pays Blanc – ancien nom breton de la ville de Guérande. Un très fin palet de chocolat 70% de cacao au sein duquel est déposé de la fleur de sel, de Guérande bien sûr... Allergènes : traces de gluten et de fruits à coque. Création L'ATTELIER / Saint Nazaire | J2: 6.5403 | K2: 0.055 | L2: =IF(K2="","",ROUND(J2*(1+K2),2)) -> 6.9 | M2: Épicerie sucrée | N2: Glucides (g) / dont sucre (g): 31 / 30 ; Protéines (g): 7 ; Matières grasses (g) / dont acides gras saturés (g): 41 / 23 ; Energie (kJ / kcal): 2262 / 544 | O2: 0.29 | P2: Oui | Q2: 101 | R2: https://abcterroirs.com/index.php?id_product=101&controller=product
A3: A-02862 | B3: A-02862 | C3: Confirmée | D3: NOIX DE CAJOU CARAMÉLISÉES LK POIVRE PIMENT TRUFFE 110g | E3: 7.9 | G3: Noix de cajou caramélisées et salées bio 110 g | H3: ATTENTION, PRODUIT ADDICTIF DU MAGASIN, NE PAS GOUTER... C'EST TROP BON ! EMBELLISSEZ VOS APÉROS AVEC CES CAJOUS SALÉES, MERCI LAURENT... OU PAS !! | I3: La noix de cajou est un véhicule parfait pour mettre en valeur une épice, ici association noix de cajou caramélisée au fameux piment d’Espelette AOP. Le croquant de la fine couche de caramel est suivi par une imbrication d’arômes sucrés salés enveloppés par la vivacité raisonnable du piment d’Espelette. Une tuerie BIS pour l'apéro. Allergènes : traces de gluten et de fruits à coque. Création Laurent : L'ATTELIER / Saint Nazaire | J3: 7.4882 | K3: 0.055 | L3: =IF(K3="","",ROUND(J3*(1+K3),2)) -> 7.9 | M3: Autres | N3: Glucides (g) / dont sucre (g): 30 / 6 ; Protéines (g): 7 ; Matières grasses (g) / dont acides gras saturés (g): 44 / 7.8 ; Energie (kJ / kcal): 2314 / 553 | O3: 0.29 | P3: Oui | Q3: 102 | R3: https://abcterroirs.com/index.php?id_product=102&controller=product
A4: A-02862 | B4: 2871 | C4: Corrigée, à vérifier OK | D4: NOIX DE CAJOU CARAMÉLISÉES LK POIVRE PIMENT TRUFFE 110g | E4: 7.9 | F4: LMB regroupe les noix caramélisées salées sous une seule réf. | G4: Noix de cajou caramélisées et poivre de Kampot bio 110 g | H4: Attention produit addictif et original pour l'apéro, le goûter c'est succomber ! | I4: La noix de cajou est un véhicule parfait pour mettre en valeur une épice donc a été associée cette noix de cajou caramélisée au poivre de Kâmpôt AOP. Le croquant de la fine couche de caramel est suivi par une combinaison d’arômes sucrés & salés enveloppés par la tonicité des deux poivres rouge et noir... Une tuerie pour l'apéro. Allergènes : traces de gluten et de fruits à coque. Création Laurent LK / Saint Nazaire | J4: 7.49 | K4: 0.055 | L4: =IF(K4="","",ROUND(J4*(1+K4),2)) -> 7.9 | M4: Autres | N4: Glucides (g) / dont sucre (g): 30 / 6 ; Protéines (g): 7 ; Matières grasses (g) / dont acides gras saturés (g): 44 / 7.8 ; Energie (kJ / kcal): 2314 / 553 | O4: 0.29 | P4: Oui | Q4: 103 | R4: https://abcterroirs.com/index.php?id_product=103&controller=product
A5: A-02830 | B5: 2839 | C5: Corrigée | D5: QUERNONS SACHET 100g (x13) | E5: 11 | G5: Quernons d'Ardoise – sachet 100 g (x13) | H5: Les Quernons d'Ardoise, la célèbre spécialité d'Angers : une fine nougatine enrobée de chocolat bleuté, en souvenir des ardoises de l'Anjou. Sachet de 13 pièces. Parfait au goûter, avec un café, ou pour garnir un coffret gourmand. Une question ? Nos cavistes vous conseillent volontiers en boutique ou au 02 40 89 76 26. | I5: Spécialité angevine gourmande sur une base nougatine et chocolat. | J5: 10.4265 | K5: 0.055 | L5: =IF(K5="","",ROUND(J5*(1+K5),2)) -> 11 | M5: Épicerie sucrée | N5: Sel (g): 10mg ; Glucides (g) / dont sucre (g): 67 / 67 ; Protéines (g): 5 ; Matières grasses (g) / dont acides gras saturés (g): 23 / 9.2 ; Energie (kJ / kcal): 2091/499 | O5: 0.12 | P5: Oui | Q5: 109 | R5: https://abcterroirs.com/index.php?id_product=109&controller=product
A6: A-01409 | B6: 2662 | C6: Corrigée | D6: PB PETIT BEURRE 70G - Maison Suzanne | E6: 4.9 | G6: Petits beurres faits à Clisson (44) 70 g | H6: En parfum disponible : noisettes cacao / sarrasin fève de tonka / caramel salé / muroise. Très artisanal et très local, l'idéal au final ! Sachet 70g | I6: Anne-Hélène est la fondatrice de Maison Suzanne. C’est en fait sa grand-mère Suzanne, qui l’a inspirée. Elle propose dans le vignoble nantais à côté de Clisson des biscuits gourmands confectionnés avec des matières premières de qualité. A découvrir ! | J6: 4.6445 | K6: 0.055 | L6: =IF(K6="","",ROUND(J6*(1+K6),2)) -> 4.9 | M6: Biscuits | O6: 0.07 | P6: Oui | Q6: 114 | R6: https://abcterroirs.com/index.php?id_product=114&controller=product
A7: A-02604 | B7: 2613 | C7: Corrigée | D7: WHISKY HELLYERS ROAD (Tasmanie) | E7: 48.9 | F7: prix LMB 48,90 € / site 52,90 € | G7: Whisky Hellyers Road – Tasmanie | I7: Incontournable de la distillerie Hellyers Road, ce single malt est produit à partir d’orge maltée locale, produite sur l’île de Tasmanie dans le sud de l’Australie. | J7: 44.08 | K7: 0.2 | L7: =IF(K7="","",ROUND(J7*(1+K7),2)) -> 52.9 | M7: Autres | N7: Degré d'alcool: 40 ; 0,7: 0,7 | O7: 1.55 | P7: Oui | Q7: 116 | R7: https://abcterroirs.com/index.php?id_product=116&controller=product
A8: A-02562 | B8: 2571 | C8: Corrigée | D8: LA PLAGE (Melon B) - Les Trois Toits | E8: 10.5 | G8: LA PLAGE (Melon B) - Les Trois Toits | H8: Muscadet devenu un joli reflet du domaine des trois toits ! | I8: Cette cuvée de printemps est toute en fraîcheur, sur de belles notes d'agrumes. A déguster au pied levé, en toute simplicité, en pique nique, et pourquoi pas à la plage ! | J8: 8.75 | K8: 0.2 | L8: =IF(K8="","",ROUND(J8*(1+K8),2)) -> 10.5 | M8: Vins de Loire | N8: Degré d'alcool: 12 ; 0,75: 0,75 | O8: 1.4 | P8: Non | Q8: 118 | R8: https://abcterroirs.com/index.php?id_product=118&controller=product
A9: A-02455 | B9: 2464 | C9: Corrigée | D9: COUP DE FOUDRE - Fessardiere | E9: 13.9 | G9: Coup de Foudre – Domaine de la Fessardière | H9: Un vrai coup de foudre pour ce vin, outre l'image, c'est du plaisir et la nouvelle génération de muscadet plus rond et charmeur ! | I9: La robe présente une belle couleur jaune. Le nez est plaisant, à la fois fruité et minéral sur le citron et la pêche. Ce vin est équilibré, rond avec ses notes citronnées et de fleur blanche. Frais et léger, ce muscadet élevé 9 mois dans un foudre de chêne ancien saura vous surprendre. | J9: 12.4167 | K9: 0.2 | L9: =IF(K9="","",ROUND(J9*(1+K9),2)) -> 14.9 | M9: Vins de Loire | N9: Degré d'alcool: 12 ; 0,75: 0,75 | O9: 1.32 | P9: Oui | Q9: 120 | R9: https://abcterroirs.com/index.php?id_product=120&controller=product
A10: A-02454 | B10: 2463 | C10: Corrigée | D10: LA MER Muscadet - Fessardière | E10: 11.9 | G10: La Mer, muscadet bio – Domaine de la Fessardière | H10: Vin en apparence classique dans un premier temps, puis un second temps où se libèrent des notes fruitées. Bref, typicité du muscadet : vivacité et salinité, puis une finale plus aromatique, que du bonheur ! BIO et consigné !! | I10: Robe jaune pâle, nez floral et fruité, notes d’agrumes, on retrouve des parfums iodés et une touche fumée. La bouche est ronde, charnue, fruitée et acidulée. | J10: 9.9167 | K10: 0.2 | L10: =IF(K10="","",ROUND(J10*(1+K10),2)) -> 11.9 | M10: Vins de Loire | N10: Degré d'alcool: 12 ; 0,75: 0,75 | O10: 1.3 | P10: Oui | Q10: 121 | R10: https://abcterroirs.com/index.php?id_product=121&controller=product
A11: A-02321 | B11: A-02321 | C11: Confirmée | D11: CINQ-CINQ Spiced Rhum Bio - Distiloire 70cl | E11: 48.5 | G11: Rhum épicé Cinq-Cinq Spiced bio – Distiloire 70 cl | I11: Rhum ambré de dégustation, le Spiced Rhum 5.5 c’est la rencontre gourmande de l’Amérique du sud et du Val de Loire autour de 5 plantes et épices. Sa double maturation de plusieurs années en fût de Bourbon puis 5 mois en fût de vin de Loire liquoreux, lui apporte caractère et élégance. Artisanal, 100% bio et naturel, sans additif ni colorant, le Spiced Rhum 5.5 est également peu sucré (seulement 20 g/L) pour une dégustation sans fausse note ! | J11: 40.4167 | K11: 0.2 | L11: =IF(K11="","",ROUND(J11*(1+K11),2)) -> 48.5 | M11: Rhums | N11: Degré d'alcool: 40 ; 0,7: 0,7 | O11: 1.5 | P11: Oui | Q11: 122 | R11: https://abcterroirs.com/index.php?id_product=122&controller=product
A12: A-02256 | B12: A-02256 | C12: Confirmée | D12: GIN Cotswolds Dry Gin - Angleterre | E12: 56.5 | G12: Gin Cotswolds Dry Gin – Angleterre | H12: Le Cotswolds Dry Gin est un gin artisanal anglais élaboré dans la région des Cotswolds. Distillé lentement en alambic pot still et titrant 46 %, il se distingue par l’utilisation d’une forte concentration de neuf botaniques dont genièvre, lavande locale, pamplemousse rose et zestes de citron vert frais. Le nez dévoile des arômes frais et épicés d’agrumes et de coriandre. En bouche, le genièvre et le pamplemousse s’équilibrent avec des notes florales et légèrement épicées. Riche en huiles essentielles, il devient légèrement trouble avec la glace ou le tonic, offrant un Gin & Tonic intense, frais et aromatique | I12: Elaboré à partir d’un spiritueux à base de blé, ce gin est infusé par macération ou par vapeur avec des botaniques de provenance locale, à savoir de la région de Cotswolds au sud-ouest de l’Angleterre. | J12: 47.0833 | K12: 0.2 | L12: =IF(K12="","",ROUND(J12*(1+K12),2)) -> 56.5 | M12: Gins | N12: Degré d'alcool: 46 ; 0,7: 0,7 | O12: 1.5 | P12: Oui | Q12: 123 | R12: https://abcterroirs.com/index.php?id_product=123&controller=product
A13: A-02254 | B13: 2263 | C13: Corrigée | D13: RHUM NEISSON Le Rhum (blanc) | E13: 42.9 | F13: prix LMB 42,90 € | G13: Rhum Neisson Le Rhum (blanc) – Martinique | H13: Festival de cannes fraîches ! Deux paramètres expliquent ce rhum blanc complexe : un sous-sol d’origine volcanique dont se nourrissent les cannes à sucre de La Thieubert et l’influence du littoral Caraïbe sur un climat très sec et ensoleillé. Neisson est le fruit d’un long travail de maturation, au cours duquel les crus sont brassés et aérés régulièrement. | J13: 33.25 | K13: 0.2 | L13: =IF(K13="","",ROUND(J13*(1+K13),2)) -> 39.9 | M13: Martinique | N13: Degré d'alcool: 52,5 ; Volume: 70cl | O13: 1.4 | P13: Oui | Q13: 124 | R13: https://abcterroirs.com/index.php?id_product=124&controller=product
A14: A-02216 | B14: A-02216 | C14: Confirmée | D14: WHISKY ARMORIK Classic | E14: 51 | G14: Whisky Armorik Classic – Bretagne | I14: Pierre angulaire de la gamme, Armorik Classic est le fruit d’un vieillissement effectué en fûts de bourbon de différents âges. Doux, onctueux et gourmand, il met en évidence la qualité du vieillissement sur la côte bretonne et l’expertise de leur maître de chai. | J14: 42.5 | K14: 0.2 | L14: =IF(K14="","",ROUND(J14*(1+K14),2)) -> 51 | M14: Whiskies français | N14: Degré d'alcool: 46 ; 0,7: 0,7 | O14: 1.4 | P14: Oui | Q14: 125 | R14: https://abcterroirs.com/index.php?id_product=125&controller=product
A15: A-02192 | B15: 2201 | C15: Corrigée | D15: COFFRET LA NANTILLAISE V2 | E15: 35.6 | G15: Coffret La Nantillaise – Grand | H15: Coffret sans alcool, bien représentatif de Nantes et du département en sucré salé | I15: Assortiment sans alcool autour du Nantillais, sirop très naturel historique de Nantes. Composition sirop 47cl (plusieurs parfums) Salé : Rillette de poisson de Loire. Sucré : tablette de chocolat torréfié à Nantes. Petit clin d'œil avec le berlingot nantais, 200g, et aussi les petits beurre de la maison Suzanne, biscuit historique de la ville. | J15: 33.7441 | K15: 0.055 | L15: =IF(K15="","",ROUND(J15*(1+K15),2)) -> 35.6 | M15: Sélection 25 à 50€ | O15: 3.5 | P15: Oui | Q15: 126 | R15: https://abcterroirs.com/index.php?id_product=126&controller=product
A16: A-05222 | B16: 2184 | C16: Corrigée | D16: COFFRET 100% SARRASIN V2 | E16: 40.8 | G16: Coffret 100 % sarrasin – Moyen | H16: Création originale autour du sarrasin, surnommé le blé noir, avec beaucoup de créations spécifiques au magasin. Le cidre est un gros succès du magasin avec cette jolie infusion de blé noir qui parfume fortement à l'ouverture et qui s'équilibre en bouche, les autres produits prouvent toute l'harmonie sucrée et salée que peut procurer cette plante bretonne. | I16: Une sélection artisanale autour du Sarrasin à dominante salée. Cidre et crème de caramel viennent de Bretagne, les autres produits du département Loire-Atlantique. Composition : cidre Kystin au blé noir torréfié (75cl), gressins de blé noir au romarin (100g), rillettes de canard au sarrasin grillé (90g), petit beurre au sarrasin et fève de tonka (90g), crème caramel salé sarrasin (40g), tablette chocolat au sarrasin (135g) | J16: 38.673 | K16: 0.055 | L16: =IF(K16="","",ROUND(J16*(1+K16),2)) -> 40.8 | M16: Sélection 25 à 50€ | O16: 3.5 | P16: Oui | Q16: 127 | R16: https://abcterroirs.com/index.php?id_product=127&controller=product
A17: A-02989 | B17: 2161 | C17: Corrigée | D17: PATE / RILLETTES LANGOUILLE (PETIT) 90g | E17: 4.9 | G17: Pâté ou rillettes à la langouille – Labbé-Simon | H17: Pâtés ou rillettes de porc mélangées avec 20% de langouille. Belle création locale. Ici pot de 90g | I17: La langouille est un produit de charcuterie artisanale. Elle est élaborée à partir de langue de porc saumurée, fumée, enveloppée dans un boyau naturel de bœuf et cuite dans un bouillon. Dans son laboratoire situé à Saint-Malo-de-Guersac, Labbe Simon en a fait sa spécialité depuis 1982. | J17: 4.6445 | K17: 0.055 | L17: =IF(K17="","",ROUND(J17*(1+K17),2)) -> 4.9 | M17: Terre | O17: 0.1 | P17: Oui | Q17: 128 | R17: https://abcterroirs.com/index.php?id_product=128&controller=product
B18: 2156 | C18: Introuvable dans LMB | G18: COFFRET ASSORTIMENT MARIN SANS ALCOOL | H18: Sélections de produits régionaux issus de la pêche de Loire ou bien de l'Atlantique. Assortiment joliment varié puisqu'on trouve une boite de sardines millésimées, tartares d'algues ou salicornes, fleur de sel de la presqu'ile de Guérande, soupe et rillettes de poissons. | I18: Rillettes de poisson de Loire - Claude Janin. Pêche traditionnelle de poissons sauvages et élaboration artisanale des recettes. 780g Soupe de poisson de l'Atlantique - Bernard Marot. Un ancien poissonnier nantais qui aujourd"hui possède sa propre conserverie en Loire Atlantique. 80g Tartare d'algues - Christine Le Tennier. Des algues bretonnes pour l'élaboration de recettes gourmandes et originales. 90g Fleur de sel de la presqu'ile de Guérande - 100g rillettes de poisson de l'Atlantique - Bernard Marot. 100g Sardines millésimées - La perles des dieux. Dessin de Delphine Cossais ou de Coralie Joulin. 115g | J18: 38.8626 | K18: 0.055 | L18: =IF(K18="","",ROUND(J18*(1+K18),2)) -> 41 | M18: Sélection 25 à 50€ | O18: 3.5 | P18: Non | Q18: 129 | R18: https://abcterroirs.com/index.php?id_product=129&controller=product
A19: A-02146 | B19: 2155 | C19: Corrigée | D19: LES GRALETTES (Fié Gris) - Eric Chevalier | E19: 14.5 | G19: Les Gralettes (fié gris) – Éric Chevalier | H19: Spécialiste du Fié Gris, Eric Chevalier nous offre une cuvée BIO idéale pour les cuisines asiatique ou exotiques ! | I19: Appelé aussi sauvignon rose, le cépage était présent sur le Val de Loire et le Haut-Poitou avant la crise phylloxérique, mais disparaît pratiquement au profit du sauvignon blanc, son plus proche cousin. Désormais, seuls quelques trop rares vignerons pratiquent à nouveau ce cépage afin de bénéficier de ses possibilités aromatiques. | J19: 12.0833 | K19: 0.2 | L19: =IF(K19="","",ROUND(J19*(1+K19),2)) -> 14.5 | M19: Vins de Loire | N19: Degré d'alcool: 13,5 ; 0,75: 0,75 | O19: 1.4 | P19: Oui | Q19: 130 | R19: https://abcterroirs.com/index.php?id_product=130&controller=product
A20: A-02114 | B20: 2123 | C20: Corrigée | D20: COFFRET NANTES SURPRENANT V2 | E20: 48 | G20: Coffret Nantes surprenant – Moyen | H20: Sélections Nantaises mais surprenantes avec quelques-uns de nos meilleurs produits. Composition :Diablotine, apéritif composé de muscadet, de rhum et de sirop de fruit originaux (75cl). Salé : Saucisson fleur de sel local, des rillettes de poissons de Loire, fondantes en bouche, travaillée sur le filet du poisson et artisanal et des petits beurre salés artisanaux. Sucré : Des raisins secs macérés dans un muscadet vendanges tardives et enrobés de chocolat noir. Petit clin d'œil sucré avec une confiture de muroise®, fruit emblématique du vignoble nantais issu d'un hybride naturel de mûre et de framboise. | I20: Diablotine (75cl). Saucisson fleur de sel local, des rillettes de poissons de Loire Janin 100g , sablés Maison Suzanne 80g. Des raisins secs enrobés de chocolat noir 90g. Une confiture de muroise® 45g. | J20: 45.4976 | K20: 0.055 | L20: =IF(K20="","",ROUND(J20*(1+K20),2)) -> 48 | M20: Sélection 25 à 50€ | O20: 3.5 | P20: Oui | Q20: 131 | R20: https://abcterroirs.com/index.php?id_product=131&controller=product
A21: A-01985 | B21: 1994 | C21: Corrigée | D21: COFFRET 100% NANTAISES V2 | E21: 53.8 | G21: Coffret 100 % Nantaises – Moyen | H21: Sélection de produits artisanaux sucrés salés et créés uniquement par des Femmes nantaises : Bérangère, Christine, Estelle, Magali, Sandrine, Anne-Hélène, , Aurore, Véronique, Charlotte. Best of de notre magasin très révélateur du départemetn Loire-Atlantique : muscadet, bière, biscuits, légumes, rillettes... | I21: Composition : Rillettes de canard les délices du petit gué (80g) Tartinable de légumes Papilles et petits plats (90g) Confiture de muroise (220g) Le sablé de la tarte bauloise (180g) Petit beurre artisanal à la fleur de sel fabriqué à Clisson par Maison Suzanne (80g) ,Vin blanc " La Mer " Domaine de la Fessardière (75cl) Bière de charlotte (75cl) | J21: 44.8333 | K21: 0.2 | L21: =IF(K21="","",ROUND(J21*(1+K21),2)) -> 53.8 | M21: Sélection plus de 50€ | O21: 4.5 | P21: Oui | Q21: 132 | R21: https://abcterroirs.com/index.php?id_product=132&controller=product
A22: A-01978 | B22: 1987 | C22: Corrigée | D22: COFFRET KIR NANTAIS v1 | E22: 49.9 | G22: Coffret Kir nantais | H22: Une collection "Made In Nantes" avec des spécialités typiques. Muscadet et sirop le nantillais sont associés pour former le kir 100% Nantais et accompagnés de déclinaisons salées autour du muscadet : saucisse et canard et de quelques autres typicités dont le dessert historique au rhum, le gâteau nantais. | I22: Composition : Muscadet fruité et minéral, par la maison Cormerais, idéal pour l'apéritif et les crustacés à marier avec Nantillais : sirop sans alcool qui existe depuis plus de 20 ans. Salé : rillettes de canard au muscadet par Bérangère 100g, saucisse sèche au muscadet par le petit Landréen 150g environ, fleur de sel de la presqu'ile de Guérande 100g. Sucré : sachet de Berlingots aux fruits 200g et gâteau nantais 130g | J22: 47.2986 | K22: 0.055 | L22: =IF(K22="","",ROUND(J22*(1+K22),2)) -> 49.9 | M22: Sélection 25 à 50€ | O22: 4.5 | P22: Oui | Q22: 133 | R22: https://abcterroirs.com/index.php?id_product=133&controller=product
A23: A-05447 | B23: 1986 | C23: Corrigée | D23: COFFRET LULU LA NANTAISE V2 | E23: 39 | G23: Coffret Lulu la Nantaise | H23: LULU la nantaise, elle en buvait au petit-déjeuner... de la liqueur de petit beurre ? | I23: Déclinaison autour du petit beurre avec des biscuits faits maison, sa boite, une liqueur au goût de biscuit ainsi qu'une pâte à tartiner. Composition : - Liqueur au délicieux goût de biscuit à déguster seul ou en nappage (20cl) - Petit beurre fabriqué avec amour à Clisson (44) au bon goût de beurre frais (70g) - Boite à l'effigie du plus célèbre petit écolier du monde - Dessous de verre LULU - tablette chocolat petit beurre | J23: 32.5 | K23: 0.2 | L23: =IF(K23="","",ROUND(J23*(1+K23),2)) -> 39 | M23: Sélection 25 à 50€ | O23: 2.5 | P23: Oui | Q23: 134 | R23: https://abcterroirs.com/index.php?id_product=134&controller=product
A24: A-01939 | B24: A-01939 | C24: Confirmée | D24: WHISKY NIKKA From The Barrel (blend) JAPON | E24: 51.5 | G24: Whisky Nikka From The Barrel (blend) – Japon | I24: Bouteille iconique du groupe Nikka, le From The Barrel représente à lui seul la maîtrise de l’assemblage nippon : puissance, finesse et équilibre. Bluffant à plus d’un titre, ce blend aux 100 whiskies confondrait plus d’un amateur qui ne jure que par les single malts. Ici, les fruits bien mûrs, voire confits donnent le change à des épices de caractère. Le tout faisant passer les 51,4% d’alcool (presque) comme une lettre à la poste … L’art de l’assemblage avec un grand A | J24: 42.9167 | K24: 0.2 | L24: =IF(K24="","",ROUND(J24*(1+K24),2)) -> 51.5 | M24: Whiskies japonais | N24: Degré d'alcool: 51,4 ; 0,5: 0,5 | O24: 1 | P24: Oui | Q24: 136 | R24: https://abcterroirs.com/index.php?id_product=136&controller=product
A25: A-01936 | B25: A-01936 | C25: Confirmée | D25: WHISKY NIKKA Coffey Grain (single grain) JAPON | E25: 59.9 | G25: Whisky Nikka Coffey Grain (single grain) – Japon | I25: Elaboré à partir d’une majorité de maïs provenant des alambics « Coffey », ce single grain nous offre un aperçu des whiskies de grain qui forment la base de tous les blends de la maison Nikka, au style particulièrement suave et charmeur. | J25: 49.92 | K25: 0.2 | L25: =IF(K25="","",ROUND(J25*(1+K25),2)) -> 59.9 | M25: Whiskies japonais | N25: Degré d'alcool: 45 ; 0,7: 0,7 | P25: Oui | Q25: 137 | R25: https://abcterroirs.com/index.php?id_product=137&controller=product
A26: A-01927 | B26: A-01927 | C26: Confirmée | D26: WHISKY KORNOG ROC'H HIR (tourbé) | E26: 71.9 | G26: Whisky Kornog Roc'h Hir (tourbé) – Bretagne | I26: Whisky tourbé, mais d'une grande finesse, élevé en fut de bourbon. Meilleur Whisky Européen en 2016 par Jim MURRAY Liquid Gold Award 94/100 - Whisky Bible 2020 | J26: 59.9167 | K26: 0.2 | L26: =IF(K26="","",ROUND(J26*(1+K26),2)) -> 71.9 | M26: Whiskies français | N26: Degré d'alcool: 46% ; Volume: 70cl | O26: 1.4 | P26: Oui | Q26: 138 | R26: https://abcterroirs.com/index.php?id_product=138&controller=product
A27: A-01895 | B27: A-01895 | C27: Confirmée | D27: WHISKY BRETON EDDU Brocéliande - PUR BLE NOIR | E27: 59.9 | G27: Whisky Eddu Brocéliande pur blé noir – Bretagne | H27: Fondée par la famille Le Lay qui était au départ dans les années 1920 des distillateurs ambulants et en 1986 ils créèrent "La distillerie des Menhirs". La distillerie familiale commença la réalisation du whisky en 1999 avec le premier du monde uniquement de blé noir. | I27: Vieilli d’abord 5 ans en fût de chêne français du Limousin, EDDU Silver Brocéliande achève sa maturation en fût de chêne neuf de la forêt de Brocéliande. Nez : boisé - floral - fruits secs Bouche : boisé - vanille - fruitées Finale : longue et raffinée | J27: 49.9167 | K27: 0.2 | L27: =IF(K27="","",ROUND(J27*(1+K27),2)) -> 59.9 | M27: Whiskies français | N27: Degré d'alcool: 42 ; Volume: 0.70 | O27: 1.7 | P27: Oui | Q27: 139 | R27: https://abcterroirs.com/index.php?id_product=139&controller=product
A28: A-01894 | B28: A-01894 | C28: Confirmée | D28: WHISKY BRETON ED GWENN (single malt) - Eddu | E28: 61.5 | G28: Whisky Eddu Ed Gwenn (single malt) – Bretagne | H28: Fondée par la famille Le Lay qui était au départ dans les années 1920 des distillateurs ambulants et en 1986 ils créèrent "La distillerie des Menhirs". La distillerie familiale commença la réalisation du whisky en 1999 avec le premier du monde uniquement de blé noir. | I28: Obtenu par distillation d’orge uniquement, Ed Gwenn est vieilli pendant plus de 4 ans en fûts de chêne français et américain. Par analogie avec Eddu qui signifie blé noir, Ed Gwenn signifie céréale blanche en breton. Nez : bananes flambées - fruits exotiques mûrs Bouche : litchi - pêche Finale : douce et élégante | J28: 51.25 | K28: 0.2 | L28: =IF(K28="","",ROUND(J28*(1+K28),2)) -> 61.5 | M28: Whiskies français | N28: Degré d'alcool: 45 ; Volume: 0.70 | O28: 1.6 | P28: Oui | Q28: 140 | R28: https://abcterroirs.com/index.php?id_product=140&controller=product
A29: A-01891 | B29: 1900 | C29: Corrigée | D29: WHISKY BRETON EDDU Gold (10ans) | E29: 81.5 | G29: Whisky Eddu Gold 10 ans – Bretagne | H29: Fondée par la famille Le Lay qui était au départ dans les années 1920 des distillateurs ambulants et en 1986 ils créèrent "La distillerie des Menhirs". La distillerie familiale commença la réalisation du whisky en 1999 avec le premier du monde uniquement de blé noir. | I29: Whisky vieillit 10 ans en fût de chêne français Nez : bois de chêne torréfié - épices Bouche : fruits pâtissiers - miel Finale : fruité - épices | J29: 67.9167 | K29: 0.2 | L29: =IF(K29="","",ROUND(J29*(1+K29),2)) -> 81.5 | M29: Whiskies français | N29: Degré d'alcool: 43 ; Volume: 0.70 | P29: Oui | Q29: 141 | R29: https://abcterroirs.com/index.php?id_product=141&controller=product
A30: A-01890 | B30: A-01890 | C30: Confirmée | D30: WHISKY BRETON EDDU Silver (100% blé noir) | E30: 52.9 | G30: Whisky Eddu Silver 100 % blé noir – Bretagne | H30: Fondée par la famille Le Lay qui était au départ dans les années 1920 des distillateurs ambulants et en 1986 ils créèrent "La distillerie des Menhirs". La distillerie familiale commença la réalisation du whisky en 1999 avec le premier du monde uniquement de blé noir. | I30: Vieilli 5 ans en fût de chêne français ayant contenu du Cognac, EDDU Silver l’original est la première édition de la gamme EDDU. Nez : agrumes - fruits frais - rose - bruyère bouche : pomme - épice - boisé très fin Finale : fraîche - fruité - équilibré | J30: 41.5833 | K30: 0.2 | L30: =IF(K30="","",ROUND(J30*(1+K30),2)) -> 49.9 | M30: Whiskies français | N30: Degré d'alcool: 43 ; Volume: 0.70 | O30: 1.7 | P30: Oui | Q30: 142 | R30: https://abcterroirs.com/index.php?id_product=142&controller=product
A31: A-01760 | B31: 1769 | C31: Corrigée | D31: TÊTE DE LARD (Cab franc) - Manoir de la Tête Rouge | E31: 16.9 | G31: Tête de Lard (cabernet franc) – Manoir de la Tête Rouge | H31: Découvrez une appellation, un terroir et un vigneron au travers de cette cuvée en BIO DYNAMIE. 100% cabernet franc. 100% racé ! | I31: Robe rouge Grenat, note de sous bois de torréfaction légèrement animal. La bouche est soyeuse vive complexe et riche. Les tannins sont présents granuleux sans astringence. La texture est crayeuse et la final est longue. Potentiel de garde de 10 ans, à 5 ans près ! | J31: 14.0833 | K31: 0.2 | L31: =IF(K31="","",ROUND(J31*(1+K31),2)) -> 16.9 | M31: Vins de Loire | N31: Degré d'alcool: 14 ; 0,75: 0,75 | O31: 1.4 | P31: Oui | Q31: 143 | R31: https://abcterroirs.com/index.php?id_product=143&controller=product
A32: A-01759 | B32: 1768 | C32: Corrigée | D32: TÊTE D'ANGE (Chenin) - Manoir de la Tête Rouge | E32: 15.5 | G32: TÊTE D'ANGE (Chenin) - Manoir Tête Rouge | H32: Saumur blanc en biodynamie, élégance et terroir ! Un grand vigneron ! Vin blanc agréablement polyvalent : viande blanche, fromage, apéro... | I32: Un joli chenin sur les terroirs de craies de Saumur. Le nez est sur la fleur blanche, la maturité du chenin est intense, des notes d’agrumes arrivent en final. En bouche, beaucoup de gras fait croire à du sucre résiduel mais le vin est sec. | J32: 12.9167 | K32: 0.2 | L32: =IF(K32="","",ROUND(J32*(1+K32),2)) -> 15.5 | M32: Vins de Loire | N32: Degré d'alcool: 14 ; 0,75: 0,75 | O32: 1.4 | P32: Non | Q32: 144 | R32: https://abcterroirs.com/index.php?id_product=144&controller=product
A33: A-02971 | B33: 1756 | C33: Corrigée | D33: RILLETTES CANARD de BERANGERE 180G | E33: 8.9 | G33: Rillettes de canard – Délices du Petit Gué 180 g | H33: Création locale et artisanale de Bérangère vers St Nazaire. Top qualité ! 180g ici au muscadet, existe aussi au sarrasin et muroise. | I33: Petite entreprise artisanale, LES DELICES DU PETIT GUE est située à Frossay au sud-ouest de Nantes. Bérangère valorise les matières premières locales : canards élevés dans les communes alentour, Muscadet et Gros Plant du vignoble nantais, Coteaux du Layon, Muroise de Vallet et sel de Guérande. | J33: 8.436 | K33: 0.055 | L33: =IF(K33="","",ROUND(J33*(1+K33),2)) -> 8.9 | M33: Épicerie salée | P33: Oui | Q33: 145 | R33: https://abcterroirs.com/index.php?id_product=145&controller=product
A34: A-02968 | B34: 1755 | C34: Corrigée | D34: RILLETTES CANARD de BERANGERE 100G | E34: 5.9 | G34: Rillettes de canard – Délices du Petit Gué 100 g | H34: Petite entreprise artisanale, LES DELICES DU PETIT GUE est située à Frossay au sud-ouest de Nantes. Bérangère valorise les matières premières locales : canards élevés dans les communes alentour, Muscadet et Gros Plant du vignoble nantais, Coteaux du Layon, Muroise de Vallet et sel de Guérande. | J34: 5.5924 | K34: 0.055 | L34: =IF(K34="","",ROUND(J34*(1+K34),2)) -> 5.9 | M34: Épicerie salée | O34: 0.2 | P34: Oui | Q34: 146 | R34: https://abcterroirs.com/index.php?id_product=146&controller=product
A35: A-01739 | B35: 1748 | C35: Corrigée | D35: TERRINE DE PORC 85G Papilles et Petits Plats PPP | E35: 5.9 | G35: Terrine de porc – Papilles et Petits Plats 85 g | I35: « Papilles et Petits Plats » est née en 2009 grâce aux délicieuses terrines que cuisinaient ses aïeuls. Depuis, Christine concocte pour vous tous les jours des terrines, des tartinables et des chutneys. Et bien sûr, les conserves « Papilles et Petits Plats » sont des produits artisanaux, locaux, sans additifs et de grande qualité ! Produits Made In Nantes. | J35: 5.59 | K35: 0.055 | L35: =IF(K35="","",ROUND(J35*(1+K35),2)) -> 5.9 | M35: Épicerie salée | O35: 0.2 | P35: Oui | Q35: 147 | R35: https://abcterroirs.com/index.php?id_product=147&controller=product
A36: A-03195 | B36: 1730 | C36: Corrigée | D36: TARTINABLE DE LEGUMES PAPILLES ET PETITS PLATS 90g PPP | E36: 5.9 | G36: Tartinables de légumes – Papilles et Petits Plats | I36: « Papilles et Petits Plats » est née en 2009 grâce aux délicieuses terrines que cuisinaient ses aïeuls. Depuis, Christine concocte pour vous tous les jours des terrines, des tartinables et des chutneys. Et bien sûr, les conserves « Papilles et Petits Plats » sont des produits artisanaux, locaux, sans additifs et de grande qualité ! Produits Made In Nantes. | J36: 5.5924 | K36: 0.055 | L36: =IF(K36="","",ROUND(J36*(1+K36),2)) -> 5.9 | M36: Végétarien | P36: Oui | Q36: 148 | R36: https://abcterroirs.com/index.php?id_product=148&controller=product
A37: A-03675 | B37: 1575 | C37: Corrigée | D37: RJA RILLETTES POISSON LOIRE de CLAUDE JANIN 100g | E37: 5.9 | G37: RILLETTES POISSONS DE LOIRE Claude janin | I37: Claude Janin, artisan pêcheur basé à St-Juline-de-Concelles, prépare des terrines et des rillettes à base des poissons qu'il a lui même pêchés, produits qui sont labellisés « poisson sauvage du bassin de la Loire », ce qui assure la traçabilité sur la date et le lieu de pêche. Parfum : brochet beurre blanc, anguilles curé nantais, silure tomate... | J37: 5.5924 | K37: 0.055 | L37: =IF(K37="","",ROUND(J37*(1+K37),2)) -> 5.9 | M37: Épicerie salée | O37: 0.2 | P37: Non | Q37: 149 | R37: https://abcterroirs.com/index.php?id_product=149&controller=product
A38: A-01546 | B38: 1555 | C38: Corrigée | D38: RHUM HAMPDEN 8 ans (Jamaïque) | E38: 78.9 | G38: RHUM HAMPDEN 8 ans - Jamaïque | I38: Ce Hampden 8 ans, digne héritier des "Stinking Rums" Jamaïcains, est un savoureux mélange de fruits mûrs, d'épices douces et de notes finement boisées. Son profil intense et ses arômes très prononcés lui confèrent un caractère authentique et naturel. | J38: 65.75 | K38: 0.2 | L38: =IF(K38="","",ROUND(J38*(1+K38),2)) -> 78.9 | M38: Caraïbes | N38: Degré d'alcool: 46 ; 0,7: 0,7 | O38: 1.6 | P38: Non | Q38: 150 | R38: https://abcterroirs.com/index.php?id_product=150&controller=product
A39: A-01509 | B39: 1518 | C39: Corrigée | D39: QUERNONS BOITE 60g (x8) | E39: 7.9 | G39: Quernons d'Ardoise – boîte 60 g (x8) | H39: Les Quernons d'Ardoise, la célèbre spécialité d'Angers : une fine nougatine enrobée de chocolat bleuté, en souvenir des ardoises de l'Anjou. Boîte de 8 pièces, jolie à offrir. Parfait au goûter, avec un café, ou pour garnir un coffret gourmand. Une question ? Nos cavistes vous conseillent volontiers en boutique ou au 02 40 89 76 26. | I39: Spécialité angevine gourmande sur une base nougatine et chocolat. | J39: 7.4882 | K39: 0.055 | L39: =IF(K39="","",ROUND(J39*(1+K39),2)) -> 7.9 | M39: Épicerie sucrée | N39: Sel (g): 10mg ; Glucides (g) / dont sucre (g): 67 / 67 ; Protéines (g): 5 ; Matières grasses (g) / dont acides gras saturés (g): 23 / 9.2 ; Energie (kJ / kcal): 2091/499 | O39: 0.12 | P39: Oui | Q39: 152 | R39: https://abcterroirs.com/index.php?id_product=152&controller=product
A40: A-01507 | B40: 1516 | C40: Corrigée | D40: QUERNONS BOITE 245g (x32) | E40: 29.9 | G40: QUERNONS BOITE 245g (x32) | I40: Spécialité angevine gourmande sur une base nougatine et chocolat. | J40: 28.3412 | K40: 0.055 | L40: =IF(K40="","",ROUND(J40*(1+K40),2)) -> 29.9 | M40: Épicerie sucrée | N40: Sel (g): 10mg ; Glucides (g) / dont sucre (g): 67 / 67 ; Protéines (g): 5 ; Matières grasses (g) / dont acides gras saturés (g): 23 / 9.2 ; Energie (kJ / kcal): 2091 / 499 | O40: 0.12 | P40: Non | Q40: 153 | R40: https://abcterroirs.com/index.php?id_product=153&controller=product
A41: A-02959 | B41: 1418 | C41: Corrigée | D41: PB PETIT BEURRE CARTE POSTALE 50G - Maison Suzanne | E41: 3.9 | F41: petit beurre carte postale 50 g | G41: Grand PETIT BEURRE NATURE avec Message 50g | H41: Petit Beurre avec message : à créer sur mesure (avec anticipation), bien sûr on peut imaginer Joyeuses fêtes... Format carte postale sympathique à offrir ou pour composer un assortiment gourmand | I41: Anne-Hélène est la fondatrice de Maison Suzanne. C’est en fait sa grand-mère Suzanne, qui l’a inspirée. Elle propose dans le vignoble nantais à côté de Clisson des biscuits gourmands confectionnés avec des matières premières de qualité. A découvrir ! | J41: 3.6967 | K41: 0.055 | L41: =IF(K41="","",ROUND(J41*(1+K41),2)) -> 3.9 | M41: Biscuits | O41: 0.05 | P41: Non | Q41: 155 | R41: https://abcterroirs.com/index.php?id_product=155&controller=product
A42: A-01407 | B42: 1416 | C42: Corrigée | D42: PBB PETIT BEURRE BOITE LU Haute Maison Suzanne 150G | E42: 15.9 | G42: Boîte petits beurres LU – Maison Suzanne 150 g | I42: Anne-Hélène est la fondatrice de Maison Suzanne. C’est en fait sa grand-mère Suzanne, qui l’a inspirée. Elle propose dans le vignoble nantais à côté de Clisson des biscuits gourmands confectionnés avec des matières premières de qualité. A découvrir ! | J42: 15.0711 | K42: 0.055 | L42: =IF(K42="","",ROUND(J42*(1+K42),2)) -> 15.9 | M42: Épicerie sucrée | O42: 0.34 | P42: Oui | Q42: 156 | R42: https://abcterroirs.com/index.php?id_product=156&controller=product
A43: A-01399 | B43: 1408 | C43: Corrigée | D43: PF PERLES FINES DU COING (melon) - Chateau du Coing | E43: 14.5 | G43: Perles Fines du Coing (melon) – Château du Coing | H43: À servir bien frais (6-8 °C), à l'apéritif, avec des huîtres ou pour une fête. Une alternative locale au champagne. Une question ? Nos cavistes vous conseillent volontiers en boutique ou au 02 40 89 76 26. | I43: L'un des rares vins pétillants de Loire Atlantique 100% melon, le cépage du Muscadet, très riche et élégant. | J43: 12.0833 | K43: 0.2 | L43: =IF(K43="","",ROUND(J43*(1+K43),2)) -> 14.5 | M43: Vins pétillants | N43: Degré d'alcool: 12 ; 0,75: 0,75 | O43: 1.6 | P43: Oui | Q43: 157 | R43: https://abcterroirs.com/index.php?id_product=157&controller=product
A44: A-01368 | B44: 1377 | C44: Corrigée | D44: PASTIS NANTAIS La Grue Jaune 70cl - Distiloire | E44: 36.9 | G44: Pastis nantais La Grue Jaune (Meskad) – Distiloire 70 cl | H44: Pastis Nantais et fier de l'être, joli succès également | I44: Médaillé d’Argent au Concours Général Agricole Paris 2020 Le Distiloire revisite la recette traditionnelle du Pastis et ses arômes typiques (anis étoilé, réglisse et herbes provençales) autour d’une sélection de plantes locales. Un mélange unique de plantes biologiques qui offre au Pastis Meskad sa richesse aromatique incomparable. Redécouvrez la fraîcheur de cette icône indémodable de l’apéritif à la française. | J44: 30.75 | K44: 0.2 | L44: =IF(K44="","",ROUND(J44*(1+K44),2)) -> 36.9 | M44: Régionale | N44: Degré d'alcool: 45 ; 0,7: 0,7 | O44: 1.4 | P44: Oui | Q44: 158 | R44: https://abcterroirs.com/index.php?id_product=158&controller=product
A45: A-01343 | B45: 1352 | C45: Corrigée | D45: ORTHOGNEISS - Domaine de l'ECU | E45: 17.9 | G45: ORTHOGNEISS, muscadet en Biodynamie Domaine de l'ECU | H45: Superbe muscadet alliant minéralité et équilibre, un grand muscadet pour redécouvrir l'appellation, par Fred Niger ! | I45: Robe Or blanc, cristalline. Nez subtil et élégant. L’attaque est souple, la bouche est complexe et tendue avec un volume imposant. Finale imposante et salivante sur le pamplemousse rose et le noyau d’amande, notes salines prononcées. Beau potentiel de garde. | J45: 14.9167 | K45: 0.2 | L45: =IF(K45="","",ROUND(J45*(1+K45),2)) -> 17.9 | M45: Vins de Loire | N45: Degré d'alcool: 12 ; 0,75: 0,75 | O45: 1.3 | P45: Non | Q45: 159 | R45: https://abcterroirs.com/index.php?id_product=159&controller=product
A46: A-01314 | B46: 1323 | C46: Corrigée, à vérifier OK | D46: NOIX DE CAJOU, AMANDE, NOISETTE, CARAMÉLISÉES LK sucrées BIO | E46: 7.9 | F46: LMB : noix caramélisées sucrées (cajou, amande, noisette) | G46: Noix de cajou caramélisées bio 100 g | I46: Cette noix de cajou vient en commerce équitable du Burkina Faso, cultivée et préparée sur place. La douceur de la noix de cajou légèrement torréfiée, enrobée d’une fine couche de caramel beurre salé pour un voyage gustatif simple et raffiné. Allergènes : traces de gluten et de fruits à coque. Création Laurent : L'ATTELIER / Saint Nazaire | J46: 7.49 | K46: 0.055 | L46: =IF(K46="","",ROUND(J46*(1+K46),2)) -> 7.9 | M46: Autres | N46: Glucides (g) / dont sucre (g): 31 / 30 ; Protéines (g): 7 ; Matières grasses (g) / dont acides gras saturés (g): 41 / 23 ; Energie (kJ / kcal): 2262 / 544 | O46: 0.29 | P46: Oui | Q46: 161 | R46: https://abcterroirs.com/index.php?id_product=161&controller=product
A47: A-01313 | B47: 1322 | C47: Corrigée | D47: NOISETTES CARAMÉLISÉES BIO 110g | E47: 7.9 | G47: NOISETTES CARAMÉLISÉES BIO 110g | I47: Une noisette italienne, de la fameuse variété Tonda e Gentile, finement caramélisée, réhaussée par une dé-cuisson du caramel au beurre de baratte breton, affinée à la fleur de sel de Guérande. Un produit aux fortes notes de noisettes torréfiées renforcées par le jeu du sucré salé du caramel. fait par Laurent et son équipe à Saint-Nazaire. | J47: 7.49 | K47: 0.055 | L47: =IF(K47="","",ROUND(J47*(1+K47),2)) -> 7.9 | M47: Autres | N47: Glucides (g) / dont sucre (g): 30 / 6 ; Protéines (g): 7 ; Matières grasses (g) / dont acides gras saturés (g): 43.85 / 7.8 ; Energie (kJ / kcal): 2314 / 533 | P47: Non | Q47: 162 | R47: https://abcterroirs.com/index.php?id_product=162&controller=product
A48: A-01311 | B48: 1320 | C48: Corrigée | D48: NOBIS (Syrah) - Domaine de l'Ecu | E48: 12.5 | G48: Nobis (syrah) – Domaine de l'Écu | I48: Cuvée vinifiée pour être sur le fruit. Un vrai vin de copains à savourer à l’apéro, sur des grillades, en famille ou pas… L’essentiel étant de prendre du plaisir et de profiter du moment présent… Vin sans chichi ni tralala ; débouchez, buvez ! | J48: 10.4167 | K48: 0.2 | L48: =IF(K48="","",ROUND(J48*(1+K48),2)) -> 12.5 | M48: Vins rouges | N48: Degré d'alcool: 14 ; 0,75: 0,75 | O48: 1.4 | P48: Oui | Q48: 163 | R48: https://abcterroirs.com/index.php?id_product=163&controller=product
A49: A-01300 | B49: 1309 | C49: Corrigée | D49: MUSCADET - LA PEPIERE | E49: 10.9 | G49: Muscadet en biodynamie – Domaine de la Pépière | H49: Bel équilibre pour ce muscadet travaillé ne biodynamie ! | I49: Un muscadet qui propose un nez fin, sur des notes fruitées et de pierre humide. En bouche, une attaque citronnée suivie d'une belle rondeur qui donne de l'amplitude et finissant sur une note tonique. Un compagnon idéal pour l'apéritif ou les repas autour des fruits de mer. | J49: 9.0833 | K49: 0.2 | L49: =IF(K49="","",ROUND(J49*(1+K49),2)) -> 10.9 | M49: Vins de Loire | N49: Degré d'alcool: 12 ; 0,75: 0,75 | O49: 1.25 | P49: Oui | Q49: 165 | R49: https://abcterroirs.com/index.php?id_product=165&controller=product
A50: A-01299 | B50: 1308 | C50: Corrigée | D50: MUSCADET ORIGINAL - Fred Lailler | E50: 13.9 | G50: Muscadet « Original » – Domaine Brégeon | H50: Muscadet au style intermédiaire, minéral et finesse, un très joli passe partout BIO ! | I50: Muscadet issu des terroirs de Gabbro de la commune de Gorges. A la fois solaire et salivant, il peut se garder quelques années en cave pour révéler tout son potentiel. | J50: 11.25 | K50: 0.2 | L50: =IF(K50="","",ROUND(J50*(1+K50),2)) -> 13.5 | M50: Vins de Loire | N50: Degré d'alcool: 12 ; 0,75: 0,75 | O50: 1.2 | P50: Oui | Q50: 166 | R50: https://abcterroirs.com/index.php?id_product=166&controller=product
A51: A-01248 | B51: 1257 | C51: Corrigée | D51: MEPHISTO (cabernet franc en amphore) - Domaine de l'Ecu | E51: 34.9 | G51: Méphisto (cabernet franc en amphore) – Domaine de l'Écu | H51: 100% cabernet franc en BIODYNAMIE, vieilli en amphore, élu meilleur vin rouge de la Loire par le RVF il y a peu ! Tout un programme pour un vin Nantais et un vigneron, Fred Niger, à découvrir... | I51: Un vin vinifié pour sublimer et respecter le Cabernet Franc, une certaine idée de la finesse et de la délicatesse, point de sur-extraction dans cette bouteille. | J51: 29.0833 | K51: 0.2 | L51: =IF(K51="","",ROUND(J51*(1+K51),2)) -> 34.9 | M51: Vins de Loire | N51: Degré d'alcool: 12 ; 0,75: 0,75 | O51: 1.6 | P51: Oui | Q51: 168 | R51: https://abcterroirs.com/index.php?id_product=168&controller=product
A52: A-01235 | B52: 1244 | C52: Corrigée | D52: MATHILDE (sauvignon) - HAUT PLANTY | E52: 9.5 | G52: Mathilde (sauvignon) – Domaine du Haut Planty | H52: Mathilde est revenue et est toujours là pour les afficionados de vin blanc sec mais fruité ! | I52: Assemblage flatteur de Sauvignon blanc et Sauvignon gris, ce vin accompagnera parfaitement les apéritifs et les repas mettant en valeur les produits de la mer. | J52: 7.9167 | K52: 0.2 | L52: =IF(K52="","",ROUND(J52*(1+K52),2)) -> 9.5 | M52: Vins de Loire | N52: Degré d'alcool: 12 ; 0,75: 0,75 | O52: 1.21 | P52: Oui | Q52: 169 | R52: https://abcterroirs.com/index.php?id_product=169&controller=product
A53: A-01221 | B53: 1230 | C53: Corrigée | D53: MALVOISIE 1/2 sec REVELATION Bio - Landron Chartier | E53: 12.5 | G53: Malvoisie demi-sec bio – Domaine Landron Chartier | H53: Malvoisie BIO sec tendre rempli de tendresse, salinité et sucrosité réunie ! | I53: Ce cépage typique de la Méditerranée est ici un cousin du pinot gris, qui se révèle à son avantage en apéro, foie gras, voire cuisine exotique ou asiatique. | J53: 10.4167 | K53: 0.2 | L53: =IF(K53="","",ROUND(J53*(1+K53),2)) -> 12.5 | M53: Vins de Loire | N53: Degré d'alcool: 11 ; 0,75: 0,75 | O53: 1.4 | P53: Oui | Q53: 170 | R53: https://abcterroirs.com/index.php?id_product=170&controller=product
A54: A-01124 | B54: 1133 | C54: Corrigée | D54: LES CLEFS (gamay) - Landron Chartier | E54: 28.9 | G54: LES CLEFS (gamay) - Landron Chartier | H54: Gamay, BIO, local et puissant ! Benoit Landron sublime le gamay d'Ancenis, un exemple ici | I54: Une cuvée atypique de Gamay du domaine Landron-Chartier : concentré, complexe, puissant. A boire sur de belles viandes rouges, ou à garder sur 10 ans | J54: 24.0833 | K54: 0.2 | L54: =IF(K54="","",ROUND(J54*(1+K54),2)) -> 28.9 | M54: Vins de Loire | N54: Degré d'alcool: 12,5 ; 0,75: 0,75 | O54: 1.7 | P54: Non | Q54: 171 | R54: https://abcterroirs.com/index.php?id_product=171&controller=product
A55: A-01078 | B55: 1087 | C55: Corrigée | D55: LA PIÈCE DE L'ORÉE (pinot noir) - Eric Chevalier | E55: 15.5 | G55: La Pièce de l'Orée (pinot noir) – Éric Chevalier | H55: 100% pinot noir local et Bio ! Eric Chevalier maitrise son sujet et propose une cuvée pour le plaisir d'un début de repas, le plaisir d'un accord sur du poisson ou de la viande blanche | I55: Cuvée de pinot noir sur les Côtes de Grand Lieu (44) qui sera vous ravir par sa finesse et son fruité intense | J55: 12.9167 | K55: 0.2 | L55: =IF(K55="","",ROUND(J55*(1+K55),2)) -> 15.5 | M55: Vins de Loire | N55: Degré d'alcool: 11,5 ; 0,75: 0,75 | O55: 1.4 | P55: Oui | Q55: 172 | R55: https://abcterroirs.com/index.php?id_product=172&controller=product
A56: A-01068 | B56: 1077 | C56: Corrigée | D56: MUSCADET LA GRUE JAUNE - Eric Chevalier | E56: 13.9 | G56: Muscadet La Grue Jaune – Éric Chevalier | H56: Anciennement le clos de la butte, la Grue jaune s'est imposée en cuvée référente et joliment clin d'oeil au passé industriel nantais. | I56: Une cuvée gourmande et ronde, qui garde beaucoup de fraîcheur. BIO par Eric Chevalier | J56: 11.5833 | K56: 0.2 | L56: =IF(K56="","",ROUND(J56*(1+K56),2)) -> 13.9 | M56: Vins de Loire | N56: Degré d'alcool: 12 ; 0,75: 0,75 | O56: 1.3 | P56: Oui | Q56: 173 | R56: https://abcterroirs.com/index.php?id_product=173&controller=product
A57: A-01003 | B57: 1012 | C57: Corrigée | D57: GWIN EVAN (Melon B) - HAUT PLANTY | E57: 12.9 | G57: Gwin Evan (melon de Bourgogne) – Domaine du Haut Planty | H57: Belle redécouverte d'un vin issu du terroir du Muscadet qui vous donnera de jolies surprises, mais pas trop. Nature ! | I57: Du Melon de Bourgogne sans soufre ajouté, plein de rondeur et de fruité, mais allégé en acidité. Du pur plaisir ! | J57: 10.75 | K57: 0.2 | L57: =IF(K57="","",ROUND(J57*(1+K57),2)) -> 12.9 | M57: Vins de Loire | N57: Degré d'alcool: 12 ; 0,75: 0,75 | O57: 1.4 | P57: Oui | Q57: 174 | R57: https://abcterroirs.com/index.php?id_product=174&controller=product
A58: A-01002 | B58: 1011 | C58: Corrigée | D58: GWENRANN LK CHOCOLAT LAIT ou NOIR FDS BIO 85g | E58: 6.9 | G58: Chocolat au lait et fleur de sel bio – Gwenrann 85 g | I58: Gwenrann, ancien nom breton de la ville de Guérande, est le nom de la première spécialité que créée par laurent et son équipe en s'installant au cœur des marais salants de Guérande. Un procédé longuement mis au point nous permet de vous faire déguster un très fin palet de chocolat 70% de cacao au sein duquel nous déposons de la fleur de sel, de Guérande bien sûr. Allergènes : traces de gluten et de fruits à coque. Création L'ATTELIER / Saint Nazaire | J58: 6.54 | K58: 0.055 | L58: =IF(K58="","",ROUND(J58*(1+K58),2)) -> 6.9 | M58: Chocolats | N58: Glucides (g) / dont sucre (g): 49 / 41 ; Protéines (g): 7 ; Matières grasses (g) / dont acides gras saturés (g): 41 / 27 ; Energie (kJ / kcal): 2462 / 589 | O58: 0.29 | P58: Oui | Q58: 175 | R58: https://abcterroirs.com/index.php?id_product=175&controller=product
A59: A-00959 | B59: A-00959 | C59: Confirmée | D59: GIN NANTAIS 1924 Distiloire 70cl | E59: 42.9 | G59: Gin nantais 1924 – Distiloire 70 cl | H59: Gin Nantais et bon, bien équilibré, un vrai succès | I59: Médaillé d’Or au Concours Général Agricole Paris 2020 Médaillé de Bronze à l’International Spirits Challenge Londres 2019 Elaboré dans la tradition du London Dry Gin anglais, le Gin 1924 est un alcool de blé biologique redistillé en présence d’une sélection unique de 8 plantes. Construit autour des baies de genièvre et de la coriandre, la trame aromatique du Gin est ici enrichie de notes florales et légèrement épicées. Cultivées en biodynamie dans le val de Loire, la camomille et l’angélique apportent élégance et structure à l’ensemble. | J59: 35.75 | K59: 0.2 | L59: =IF(K59="","",ROUND(J59*(1+K59),2)) -> 42.9 | M59: Gins | N59: Degré d'alcool: 43 | O59: 1.4 | P59: Oui | Q59: 176 | R59: https://abcterroirs.com/index.php?id_product=176&controller=product
A60: A-00958 | B60: A-00958 | C60: Confirmée | D60: GIN Heol An Oriant 70CL (épicé,sec,frais) - Gorvello - Bretagne | E60: 45.9 | G60: Gin Heol An Oriant bio – Gorvello 70 cl | H60: 17 botaniques ! Pour base des baies de genièvre et des graines de coriandre auxquelles ont été associées des épices et aromates lointaines (cardamome, poivre de cubèbe, cannelle de Ceylan, noix de muscade…), des plantes et fleurs traditionnellement employées dans la pharmacopée bretonne (réglisse, angélique, sureau…) ainsi que des zestes de citron, d’orange amère et un soupçon de gingembre frais. | J60: 38.25 | K60: 0.2 | L60: =IF(K60="","",ROUND(J60*(1+K60),2)) -> 45.9 | M60: Gins | N60: Degré d'alcool: 42 ; Volume: 70cl | O60: 1.1 | P60: Oui | Q60: 177 | R60: https://abcterroirs.com/index.php?id_product=177&controller=product
A61: A-00883 | B61: 892 | C61: Corrigée | D61: FOLLE BLANCHE LA PART DU COLIBRI - LE FAY D'HOMME | E61: 10.9 | G61: FOLLE BLANCHE LA PART DU COLIBRI | H61: Redécouvrez les jolies vertus du Gros Plant au travers du travail BIO des Caillé | I61: Vin de couleur pâle à reflet vert typique du cépage dont il est issu : la folle blanche. Frais et nerveux, il dévoile également des notes minérales. | J61: 9.0833 | K61: 0.2 | L61: =IF(K61="","",ROUND(J61*(1+K61),2)) -> 10.9 | M61: Vins de Loire | N61: Degré d'alcool: 11,5 ; 0,75: 0,75 | O61: 1.3 | P61: Non | Q61: 178 | R61: https://abcterroirs.com/index.php?id_product=178&controller=product
A62: A-00624 | B62: 633 | C62: Corrigée | D62: CLISSON (cru communal) - Domaine des Cognettes | E62: 18.5 | G62: Clisson – Domaine des Cognettes | H62: Cru communal très réputé, des muscadets travaillés différemment pour plus s'apparenter naturellement à des vins de Bourgogne | I62: Belle robe limpide jaune claire aux reflets dorés. Un nez riche et complexe mêlant à la fois des fruits jaunes mûrs et des notes lactées, beurrées et légèrement citronnées. Une bouche onctueuse et structurée avec une finale tendue et très longue. | J62: 15.4167 | K62: 0.2 | L62: =IF(K62="","",ROUND(J62*(1+K62),2)) -> 18.5 | M62: Vins de Loire | N62: Degré d'alcool: 13,5 ; 0,75: 0,75 | O62: 1.35 | P62: Oui | Q62: 182 | R62: https://abcterroirs.com/index.php?id_product=182&controller=product
A63: A-00566 | B63: 575 | C63: Corrigée | D63: CHARDONNAY "LES 3 BOIS" - Eric Chevalier | E63: 12.5 | G63: Chardonnay « Les 3 Bois » – Éric Chevalier | H63: Eric Chevalier met en valeur par une belle minéralité et un bel équilibre ce chardonnay, travaillé en bio, version 100% locale en final | I63: Simplicité et éclat du cépage chardonnay sur nos sols légers et géographie maritime. | J63: 10.4167 | K63: 0.2 | L63: =IF(K63="","",ROUND(J63*(1+K63),2)) -> 12.5 | M63: Vins de Loire | N63: Degré d'alcool: 12,5 ; 0,75: 0,75 | O63: 1.4 | P63: Oui | Q63: 183 | R63: https://abcterroirs.com/index.php?id_product=183&controller=product
A64: A-00557 | B64: 566 | C64: Corrigée | D64: CHAMPAGNE Pure Meunier (brut nature) - Moutardier | E64: 37.9 | G64: Champagne brut Pure Meunier – Moutardier | H64: Superbe champagne de vignerons indépendants sur une base 100% Pinot Meunier pour une expression pure et minérale, très joliment à l'ancienne ! | I64: Ce vin de pure origine est un Champagne pour amateurs passionnés et découvreurs de vins inédits. Insolite, la Cuvée Pure Meunier allie fraîcheur, minéralité, fruité et tendresse. Un Champagne épuré et harmonieux qui s’offre dans sa plénitude. | J64: 31.5833 | K64: 0.2 | L64: =IF(K64="","",ROUND(J64*(1+K64),2)) -> 37.9 | M64: Autres vignobles | N64: Degré d'alcool: 12 ; 0,75: 0,75 | O64: 1.7 | P64: Oui | Q64: 184 | R64: https://abcterroirs.com/index.php?id_product=184&controller=product
A65: A-00555 | B65: 564 | C65: Corrigée | D65: CHAMPAGNE BRUT CARTE D'OR Moutardier | E65: 27.9 | G65: Champagne brut Carte d'Or – Moutardier | H65: Champagne de récoltant sur une base de cépages : 80% Meunier - 15% Chardonnay - 5% Pinot Noir, qui donne une cuvée pleine de finesse et d'équilibre en bouche. Valeur plus que sûre ! | I65: Le Champagne d’apéritif, du partage en toute simplicité. La générosité, l’ampleur et la fraîcheur sont ses attributs majeurs. Crustacés et agrumes en galette de blé noir : un contraste apporté par une certaine maturité fruitée du vin. | J65: 23.25 | K65: 0.2 | L65: =IF(K65="","",ROUND(J65*(1+K65),2)) -> 27.9 | M65: Autres vignobles | N65: Degré d'alcool: 12 ; 0,75: 0,75 | O65: 1.7 | P65: Oui | Q65: 185 | R65: https://abcterroirs.com/index.php?id_product=185&controller=product
A66: A-00533 | B66: 542 | C66: Corrigée | D66: CARPE DIEM (melon en Amphore) - Domaine de l'Ecu | E66: 39.9 | G66: Carpe Diem (melon en amphore) – Domaine de l'Écu | H66: Vin de gastronomie, vieilli en amphores et travaillé en biodynamie pour une expression surréaliste de ce cépage phare Nantais, à accommoder "tout simplement" sur du homard, st jacques ou pintade. | I66: Un vin vinifié 15 mois en amphores qui montre une nouvelle expression du Melon de Bourgogne | J66: 33.25 | K66: 0.2 | L66: =IF(K66="","",ROUND(J66*(1+K66),2)) -> 39.9 | M66: Vins de Loire | N66: Degré d'alcool: 12 ; 0,75: 0,75 | O66: 1.5 | P66: Oui | Q66: 186 | R66: https://abcterroirs.com/index.php?id_product=186&controller=product
A67: A-00496 | B67: 505 | C67: Corrigée | D67: CABECÔT (cab frc - côt) - Bonnet Huteau | E67: 12.5 | F67: LMB : « Cabecôt » | G67: CABERNET COT Bonnet Huteau | H67: Travail en biodynamie dans le pays Nantais pour un vin rouge qui offrira un bel équilibre et une puissance maitrisée. Domaine Bonnet Huteau. | I67: Cet emballage de deux cépages possède des arômes de fruits rouges et d’épices fraîches. C’est un vin à la fois souple et bien équilibré. | J67: 10.4167 | K67: 0.2 | L67: =IF(K67="","",ROUND(J67*(1+K67),2)) -> 12.5 | M67: Vins de Loire | N67: Degré d'alcool: 12,5 ; 0,75: 0,75 | O67: 1.33 | P67: Non | Q67: 187 | R67: https://abcterroirs.com/index.php?id_product=187&controller=product
A68: A-00419 | B68: 428 | C68: Corrigée | D68: BILLES DE ROCHE ROUGE (cabernet) - Melaric | E68: 22.9 | G68: BILLES DE ROCHE ROUGE (cabernet) Melaric | H68: Superbe micro appellation à découvrir Puy Notre Dame, joli contresens aux saumurs rouges classiques et légers, ici vin puissamment surprenant à 14° en Bio | I68: Un Cabernet franc généreux, alliant un nez frais à une bouche puissante et expressive. Ce vin offre aussi un beau potentiel de garde | J68: 17.4167 | K68: 0.2 | L68: =IF(K68="","",ROUND(J68*(1+K68),2)) -> 20.9 | M68: Vins de Loire | N68: Degré d'alcool: 13 ; 0,75: 0,75 | O68: 1.4 | P68: Non | Q68: 193 | R68: https://abcterroirs.com/index.php?id_product=193&controller=product
A69: A-00314 | B69: 323 | C69: Corrigée | D69: ATMOSPHÈRES (folle B - pinot N - Chardo) - Jo Landron | E69: 18.5 | G69: Atmosphères (folle blanche, pinot noir, chardonnay) – Jo Landron | H69: Bulles locales sur assemblage de trois cépages : folle blanche, pinot noir et chardonnay. Très bien équilibrée et légèrement fruitée. par Jo LANDRON | I69: Nez frais, floral et fruité (groseille, poire). Bouche vive, rafraichissante aux notes de coing et légèrement briochée, avec une finale tranchante d'une pureté cristalline. | J69: 15.4167 | K69: 0.2 | L69: =IF(K69="","",ROUND(J69*(1+K69),2)) -> 18.5 | M69: Vins pétillants | N69: Degré d'alcool: 12 ; 0,75: 0,75 | O69: 1.6 | P69: Oui | Q69: 195 | R69: https://abcterroirs.com/index.php?id_product=195&controller=product
A70: A-00292 | B70: 301 | C70: Corrigée | D70: AMPHIBOLITE (muscadet) - Jo Landron | E70: 15.9 | G70: Amphibolite, muscadet – Jo Landron | H70: Muscadet parmi les plus réputés, travaillé en biodynamie. Plus que parfait sur huitres et fruits de mer. Par Jo Landron, une des références en local, surnommé l'Astérix du vignoble pour tout son travail de valorisation de l'appellation. | I70: Vin avec une belle spontanéité d’arôme : agrume et salinité en fin de bouche. Ici, le vin a choisi l’expression de la jeunesse. | J70: 13.25 | K70: 0.2 | L70: =IF(K70="","",ROUND(J70*(1+K70),2)) -> 15.9 | M70: Vins de Loire | N70: Degré d'alcool: 11,5 ; 0,75: 0,75 | O70: 1.3 | P70: Oui | Q70: 198 | R70: https://abcterroirs.com/index.php?id_product=198&controller=product
A71: A-00289 | B71: 298 | C71: Corrigée | D71: AMANDES CARAMÉLISEÉS BIO 110g | E71: 7.9 | G71: Amandes caramélisées bio 110 g | H71: Création gourmande faites à Saint Nazaire, bien équilibrée sur son caramélisé. Bio de surcroit. | I71: Laurent a créé ici une amande italienne, finement caramélisée, rehaussée par une dé-cuisson du caramel au beurre de baratte breton, affinée à la fleur de sel de Guérande. Un produit simple et raffiné à la fois. Allergènes : traces de gluten et de fruits à coque. Produit à Saint Nazaire | J71: 7.49 | K71: 0.055 | L71: =IF(K71="","",ROUND(J71*(1+K71),2)) -> 7.9 | M71: Autres | N71: Glucides (g) / dont sucre (g): 30 / 6 ; Protéines (g): 7 ; Matières grasses (g) / dont acides gras saturés (g): 43.85 / 7.78 ; Energie (kJ / kcal): 2314 / 553 | P71: Oui | Q71: 199 | R71: https://abcterroirs.com/index.php?id_product=199&controller=product
A72: A-00275 | B72: 284 | C72: Corrigée | D72: ABOURIOU ANCRE - HAUT PLANTY | E72: 13.5 | G72: Abouriou Ancre (cuve) – Domaine du Haut Planty | H72: Cépage typique à découvrir, autrefois vin de soif des vignerons, il s'exprimera sur sa fraicheur et des notes fruits noirs confits et légèrement épicées. Vin naturel, naturellement bon ! | I72: Cépage modeste et rustique issu du sud-ouest. Cette jeune vigne offre une vendange très saine, vinifié en macération carbonique pendant 8 à 10 jours. La couleur et les tannins sont vite au rendez-vous. Le pressurage réalisé, les jus fermentent en cuve souterraine, la mise en bouteilles se fera 12 à 15 mois plus tard, sans soufre ajouté. | J72: 10.4167 | K72: 0.2 | L72: =IF(K72="","",ROUND(J72*(1+K72),2)) -> 12.5 | M72: Vins de Loire | N72: Degré d'alcool: 12 ; 0,75: 0,75 | O72: 1.4 | P72: Oui | Q72: 200 | R72: https://abcterroirs.com/index.php?id_product=200&controller=product
A73: A-06309 | C73: Ajoutée | D73: COFFRET PACK APERO NANTAIS | E73: 25.2 | G73: Pack apéro nantais | H73: Coffret pack apéro Nantais avec des bières locales et consignées, saucisson nantais, rillettes de canard et de saumon... | I73: Deux bières nantaises en 33cl : Nanmet blanche à la fève de tonka et blonde désaltérante style allemand, deux bières bios locales et consignées. Accompagnées d'un saucisson fait au Landreau au sel de Guérande (environ 200g, des rillettes de canard 100g faites à Frossay et une petit pot de rillettes de saumon au citron vert 50g fait à Malville | J73: 23.8863 | K73: 0.055 | L73: =IF(K73="","",ROUND(J73*(1+K73),2)) -> 25.2 | M73: Sélection moins de 25€ | O73: 2.5 | P73: Oui | Q73: 230 | R73: https://abcterroirs.com/index.php?id_product=230&controller=product
A74: A-05292 | C74: Ajoutée | D74: COFFRET LA NANTILLAISE V1 | E74: 18.5 | G74: Coffret La Nantillaise – Petit | H74: Sélection symbolique et Nantaise autour du Nantillais | I74: Nantillais, sirop historique pour faire des kirs ou prendre tel quel, 47cl. Petits beurres artisanaux faits à cote de Clisson, sachet de 3 biscuits à la fleur de sel. Sachet de berlingots nantais 100g. Sardine au chocolat au lait. Rillette de poisson de l'Atelier Marot 45g. | J74: 17.5355 | K74: 0.055 | L74: =IF(K74="","",ROUND(J74*(1+K74),2)) -> 18.5 | M74: Sélection moins de 25€ | O74: 2.5 | P74: Oui | Q74: 231 | R74: https://abcterroirs.com/index.php?id_product=231&controller=product
A75: A-02104 | C75: Ajoutée | D75: COFFRET FARANDOLE TERRE ET MER 44 | E75: 38 | G75: Farandole terre et mer nantaise | H75: Très bel assortiment Nantais avec cette sélection de 6 rillettes locales : 3 de la Mer (et de la Loire) et 3 de la Terre, pour 6 producteurs locaux différents. Qualité et artisanat au RV | I75: En Mer : rillettes de bar au chorizo par Marot, rillettes de poissons de Loire aux écrevisses par Arnaud guéret, rillettes de sandre revisitées avec du foie gras par Claude Janin En Terre : rillettes de canard au muscadet par Bérangère à Frossay, pâté de Langouille (spécialité autour de la langue de porc confites, fumées...) par Labbé-Simon et rillettes de proc au sarrasin par Christine à Nantes | J75: 36.019 | K75: 0.055 | L75: =IF(K75="","",ROUND(J75*(1+K75),2)) -> 38 | M75: Sélection 25 à 50€ | O75: 1.5 | P75: Oui | Q75: 232 | R75: https://abcterroirs.com/index.php?id_product=232&controller=product
A76: A-05290 | B76: 1994 | C76: Corrigée | D76: COFFRET 100% NANTAISES V3 | E76: 75.7 | G76: Coffret 100 % Nantaises – Grand | H76: Sélection sucrée salée de produits artisanaux créés uniquement par des femmes nantaises : Bérangère, Christine, Estelle, Magali, Sandrine, Anne-Hélène, Camille, Gwen, Aurore, Véronique, Charlotte, Anne. Belle présentation dans une bourriche que nous filmons et décorons. Panier historique et assumé de notre enseigne ! | I76: Composition : Rillettes de canard les délices du petit gué (80g) Tartinables de légumes Papilles et petits plats (90g) et Ho Op, Confiture de muroise (220g) Le sablé de la tarte bauloise (180g), petits beurres artisanaux à la fleur de sel (80g) par Anne-Helene, Les craquant d'amande de l'atelier de Valérie (100g). Boissons : Vin blanc Muscadet "La Mer" Domaine de la Fessardière (75cl) , Bière de Charlotte (75cl), sirop bio à la fraise par Anne (25cl) | J76: 71.7536 | K76: 0.055 | L76: =IF(K76="","",ROUND(J76*(1+K76),2)) -> 75.7 | M76: Sélection plus de 50€ | O76: 4.5 | P76: Oui | Q76: 237 | R76: https://abcterroirs.com/index.php?id_product=237&controller=product
A77: A-01411 | C77: Ajoutée, à vérifier OK | D77: PBB PETIT BEURRE PETITE BOITE Maison Suzanne 35G | E77: 5.9 | F77: LMB : petite boîte Maison Suzanne 35 g | G77: Petite boîte Petit Écolier LU avec petits beurres | H77: Très jolie boite à savon ici avec des petits beurres artisanaux faits à côté de Clisson | I77: Sachet de 4 petits beurres faits par Anne-Hélène à la fleur de sel de Guérande (40g) Boite à savon : 9.5 x 6 x2.7cm | J77: 4.9167 | K77: 0.2 | L77: =IF(K77="","",ROUND(J77*(1+K77),2)) -> 5.9 | M77: Sélection moins de 25€ | O77: 0.007 | P77: Oui | Q77: 238 | R77: https://abcterroirs.com/index.php?id_product=238&controller=product
A78: A-00444 | B78: 3245 | C78: Introuvable dans LMB OK | F78: LMB : seulement la boîte plate vide | G78: Boîte Tour LU plate avec petits beurres | H78: Boite plate et en relief sur la tour LU avec des petits beurres artisanaux et très gourmands faits vers Clisson par Anne-Hélène, format spécial qui plait beaucoup en magasins. Le vrai petit beurre artisanal et local ! | I78: Composition : petits beurres à la fleur de sel de Guérande 150g | J78: 14.1232 | K78: 0.055 | L78: =IF(K78="","",ROUND(J78*(1+K78),2)) -> 14.9 | M78: Sélection moins de 25€ | P78: Oui | Q78: 239 | R78: https://abcterroirs.com/index.php?id_product=239&controller=product
A79: A-00022 | B79: 2244 | C79: Corrigée, à vérifier Ok | D79: BOITE SUCRETTE TOUR LU NANTES Caramels Salés du Croisic 100g | E79: 9.9 | F79: LMB : boîte sucrette Tour LU caramels du Croisic 9,90 € | G79: Boîte sucrette Tour LU garnie – Petite | H79: Jolie petite boite contenant un sachet de berlingots nantais et un sachet de petits beurres à la fleur de sel faits vers Clisson. Simple mais efficace avec aussi une boite qui va rester en trace du cadeau. Petits beurres personnalisables via un texte ou logo (surcoût à voir) | I79: Composition : berlingots nantais de 100g et un sachet de petits beurres à la fleur de sel 28g. | J79: 8.25 | K79: 0.2 | L79: =IF(K79="","",ROUND(J79*(1+K79),2)) -> 9.9 | M79: Sélection moins de 25€ | O79: 0.5 | P79: Oui | Q79: 240 | R79: https://abcterroirs.com/index.php?id_product=240&controller=product
A80: A-02825 | B80: 2245 | C80: Corrigée, à vérifier | D80: boite sucrette TOUR LU V2 | E80: 15.9 | F80: LMB : boîte sucrette Tour LU V2 | G80: Boîte sucrette Tour LU garnie – Grande | H80: Assortiment de spécialités illustrant Nantes et ses gourmandises, idéal pour des cadeaux pour événements (salons...). Boite LU avec couvercle en relief et notamment des petits beurres artisanaux à l'intérieur. Petits beurres qui peuvent être personnalisés à la demande (surcoût à voir) | I80: Petite et jolie boite avec visuel Tour LU contenant un sachet de berlingots nantais 100g, des petits beurres à la fleur de sel très gourmands 28g, un sachet de fleur de sel 50g de la presqu'ile de Guérande, un pot de crème de caramel salé 50g et une sardine au chocolat au lait avec éclat de crêpe dentelle. Cette composition reste un exemple, n'hésitez pas à nous contacter... | J80: 15.0711 | K80: 0.055 | L80: =IF(K80="","",ROUND(J80*(1+K80),2)) -> 15.9 | M80: Sélection moins de 25€ | O80: 0.7 | P80: Oui | Q80: 241 | R80: https://abcterroirs.com/index.php?id_product=241&controller=product
A81: A-01975 | B81: 1975 | C81: Corrigée | D81: COFFRET FOLIE FOIE GRAS | E81: 57.1 | G81: Coffret Folie foie gras | H81: Délectations autour d'un foie gras de canard entier d'origine Bretonne à la fine de Bretagne et fleur de sel de Guérande qui s'exprimera à la perfection sur des toasts 100% blé noir et d'un confit d'oignons bio local. Nous le proposons avec une bouteille demi sec typique et rare de malvoisie, en bio, fait vers Ancenis, avec un petit accompagnement délicat de raisins chocolatés macérés dans du muscadet issu de vendanges tardives. | I81: Composition : foie gras de canard entier d'origine Bretonne à la fine de Bretagne et fleur de sel de Guérande 120g, toasts multi-graines 100% blé noir, confit d'oignons bio 90g, malvoisie bio 75cl, raisins chocolatés macérés dans du muscadet issu de vendanges tardives 80g. | J81: 54.1232 | K81: 0.055 | L81: =IF(K81="","",ROUND(J81*(1+K81),2)) -> 57.1 | M81: Sélection plus de 50€ | O81: 3.5 | P81: Oui | Q81: 242 | R81: https://abcterroirs.com/index.php?id_product=242&controller=product
A82: A-04170 | C82: Ajoutée | D82: COFFRET VOYAGE EXTRAORDINAIRE V2 | E82: 53.8 | G82: Coffret Voyage extraordinaire – Moyen | H82: Belle sélection Nantaise autour d'un muscadet Bio typé Jules Verne par ses jolies étiquettes (trois créations). | I82: Muscadet 75cl bio par la famille Lieaubeau, bien équilibré, légèrement fruité. Bière de la brasserie Nautille à Rezé 75cl. Raisins chocolats macérés dans du muscadet vendanges tardives (création du magasin) sachet de 90g. Noix de cajou caramélisées au poivre de Kampot, Petit pâté à la Langouille 90g, la Langouille existe depuis 30 ans dans le département c'est une spécialité de langues de porc. Sablés apéritif de Vincent pour le clin d'œil à notre fromage local le curé nantais. Sur la photo, il y a les rillettes de poissons de Loire 100g de Claude Janin, mais Claude prend sa retraite, elles sont remplacées par les rillettes de poissons d'Arnaud Guéret pêcheur à Varades, possiblement avec de la Lamproie au malvoisie, hyper intéressante en texture et gout ! | J82: 50.9953 | K82: 0.055 | L82: =IF(K82="","",ROUND(J82*(1+K82),2)) -> 53.8 | M82: Sélection plus de 50€ | O82: 2.1 | P82: Oui | Q82: 243 | R82: https://abcterroirs.com/index.php?id_product=243&controller=product
A83: A-04066 | B83: Rhum Barbancourt trois étoiles 4 ans | C83: Corrigée | D83: RHUM BARBANCOURT TROIS ETOILE 4 ANS | E83: 39.9 | G83: Rhum Barbancourt 4 ans Trois étoiles - Haïti | H83: La distilleries Barbancourt produit des rhums pur jus de canne à sucre, de fait il est un rhum agricole. Il prouve tout l'immense savoir-faire de l'emblématique distillerie fondée en 1862. Nez : léger et frais sur des notes d'épices, de vanille et de caramel craquant Bouche : légère et vive avec des arômes de chêne, de vanille, de beurre et d'épices Finale : douce | J83: 33.25 | K83: 0.2 | L83: =IF(K83="","",ROUND(J83*(1+K83),2)) -> 39.9 | M83: Caraïbes | O83: 1.3 | P83: Non | Q83: 244 | R83: https://abcterroirs.com/index.php?id_product=244&controller=product
A84: A-01555 | C84: Ajoutée | D84: RHUM PLANTERAY Gran Anejo Guatemala Belize | E84: 44.5 | F84: Plantation s'appelle maintenant Planteray | G84: Rhum Plantation Gran Añejo – Guatemala | H84: Plantation Rum Gran Anejo provient de l'assemblage de différents rhums du Guatemala, âgés entre 3 et 4 ans, vieillis en fûts de bourbon dans les Caraïbes, puis affinés dans de vieux fûts de chêne français au Château de Bonbonnet. Très riche, il est marqué par des notes d'agrumes confits et de raisins secs, de pivoine, de fruit de la passion et d'épices. | J84: 37.0833 | K84: 0.2 | L84: =IF(K84="","",ROUND(J84*(1+K84),2)) -> 44.5 | M84: Amérique Latine | N84: Degré d'alcool: 42% ; Volume: 70cl | O84: 1.3 | P84: Oui | Q84: 245 | R84: https://abcterroirs.com/index.php?id_product=245&controller=product
A85: A-04087 | C85: Ajoutée | D85: RHUM FONTANEL BLANC - RHUMERIE DU VIGNOBLE | E85: 44.9 | G85: Rhum Fontanel blanc – Rhumerie du Vignoble | H85: Produit au cœur du vignoble nantais ce rhum 100% artisanal, à Saint Fiacre sur Maine, à base de mélasse de canne à sucre Bio du Paraguay. Tout y est fait sur place, fermentations, distillations et embouteillage. Il saura vous séduire avec ses parfums de cannes cuites et son onctuosité. Le parfait compagnon pour vos ti 'punchs ou cocktails. | J85: 37.4167 | K85: 0.2 | L85: =IF(K85="","",ROUND(J85*(1+K85),2)) -> 44.9 | M85: Régionale | N85: Degré d'alcool: 44% ; Volume: 70cl | O85: 1.7 | P85: Oui | Q85: 258 | R85: https://abcterroirs.com/index.php?id_product=258&controller=product
A86: A-04088 | C86: Ajoutée | D86: RHUM FONTANEL SPICED - RHUMERIE DU VIGNOBLE | E86: 49.9 | G86: Rhum Fontanel Spiced – Rhumerie du Vignoble | H86: Produit au cœur du vignoble nantais ce rhum 100% artisanal, à Saint Fiacre sur Maine, à base de mélasse de canne à sucre Bio du Paraguay. Tout y est fait sur place, fermentations, distillations et embouteillage. Affiné dans d'ancien fûts de Sherry, avec une macération d'épices gourmandes. Vanille, cannelle, muscade, poivre, clous de girofle et caramel. Aucune épices ne vient en écraser une autre. Le résultat est flatteur avec cette sensation de caramel mou vanillé mais sans tombé dans l'excès de sucre. | J86: 41.5833 | K86: 0.2 | L86: =IF(K86="","",ROUND(J86*(1+K86),2)) -> 49.9 | M86: Amérique Latine | N86: Degré d'alcool: 40% ; Volume: 70cl | O86: 1.7 | P86: Oui | Q86: 259 | R86: https://abcterroirs.com/index.php?id_product=259&controller=product
A87: A-03506 | C87: Ajoutée | D87: RHUM SOL TARASCO 8 ANS - Mexique | E87: 54.5 | G87: RHUM SOL TARASCO 8 ANS - Mexique | H87: Sol Tarasco est produit à partir de jus de canne à sucre locale mexicaine AOC, ce qui en fait un rhum agricole. Elles poussent sur un sol rouge volcanique à de plus de 1 270 mètres d’altitude. Une fois distillé, il est vieilli dans d'anciens fûts de bourbons et de sherry. Les parfums sont suaves, vanillés et les parfums de canne sont mis en valeur. En bouche, c'est une explosion de saveurs. Bois grillé, vanillé, compoté de mangue tout en ayant une texture fraîche. | J87: 43.75 | K87: 0.2 | L87: =IF(K87="","",ROUND(J87*(1+K87),2)) -> 52.5 | M87: Amérique Latine | N87: Degré d'alcool: 40% ; Volume: 70cl | O87: 1.2 | P87: Non | Q87: 260 | R87: https://abcterroirs.com/index.php?id_product=260&controller=product
A88: A-01531 | B88: A-04064 | C88: Corrigée, à vérifier OK | D88: RHUM BARBANCOURT 8 ans | E88: 39.9 | F88: LMB : Barbancourt 8 ans à 39,90 € ; l'ancienne réf. A-04064 n'existe plus | G88: Rhum Barbancourt 8 ans Réserve Spéciale - Haïti | H88: La distilleries Barbancourt produit des rhums pur jus de canne à sucre, de fait il est un rhum agricole. Nez : vanillé, poivré Bouche : puissante, notes torréfiées, fruits cuits (pruneaux), marmelade Finale : intense Il prouve tout l'immense savoir-faire de l'emblématique distillerie fondée en 1862. | J88: 43.75 | K88: 0.2 | L88: =IF(K88="","",ROUND(J88*(1+K88),2)) -> 52.5 | M88: Rhums | N88: Degré d'alcool: 43% ; Volume: 70cl | O88: 1.3 | P88: Non | Q88: 261 | R88: https://abcterroirs.com/index.php?id_product=261&controller=product
A89: A-03902 | C89: Ajoutée, à vérifier OK | D89: RHUM MONTEBELLO RHUM VIEUX 3ANS | E89: 49.9 | F89: LMB a 2 fiches Montebello 3 ans : A-03902 et A-03523 | G89: RHUM MONTEBELLO 3 ANS | H89: Initialement appeler "Carrière" la distillerie créée en 1930 fut racheté par la famille Marsolle en 1968, ils décident alors de la moderniser et de relancer la production. Montebello a la spécificité de placer les fûts de chêne dans des conteneurs métalliques pour accélérer le processus de vieillissement, alors que d'autres distilleries cherchent à réduire la part des anges. Nez : gourmand, pâtissier, vanille douce Bouche : canne à sucre, mangue verte, chêne grillé Finale : longue, gourmande, fruits confits | I89: Comme tous les rhums de la distillerie Montebello, il est vieilli en fûts de chêne. Le rhum 3 ans d'âge est le seul assemblage de la gamme. Il contient 3 ans d'âge (70%), 8 ans d'âge (20%) et 12 ans d'âge (10%), ce qui fait une moyenne de près de 5 ans d'âge, mais la législation oblige à ne mentionner que l'âge le plus jeune sur l'étiquette. | J89: 41.5833 | K89: 0.2 | L89: =IF(K89="","",ROUND(J89*(1+K89),2)) -> 49.9 | M89: Guadeloupe | O89: 1.4 | P89: Non | Q89: 262 | R89: https://abcterroirs.com/index.php?id_product=262&controller=product
A90: A-03903 | C90: Ajoutée | D90: RHUM MONTEBELLO RHUM VIEUX MILLÉSIME 8ANS | E90: 89.9 | G90: RHUM MONTEBELLO 8 ANS | H90: Initialement appeler "Carrière" la distillerie créée en 1930 fut racheté par la famille Marsolle en 1968, ils décident alors de la moderniser et de relancer la production. Montebello a la spécificité de placer les fûts de chêne dans des conteneurs métalliques pour accélérer le processus de vieillissement, alors que d'autres distilleries cherchent à réduire la part des anges. Nez : intense, pâtissier Bouche : canne à sucre toasté, épices, fruits secs Finale : longue, riche, banane flambé | I90: La qualité de ce rhum très vieux Montebello 6 ans est obtenue par un vieillissement en fûts de chêne américain de 180 litres ayant contenus du bourbon. | J90: 74.9167 | K90: 0.2 | L90: =IF(K90="","",ROUND(J90*(1+K90),2)) -> 89.9 | M90: Guadeloupe | O90: 1.5 | P90: Non | Q90: 263 | R90: https://abcterroirs.com/index.php?id_product=263&controller=product
A91: A-03658 | C91: Ajoutée | D91: RHUM BÊTE A FEU blanc - Martinique | E91: 43.5 | G91: Rhum Bête à Feu – A1710 | H91: A 1710 est une jeune distillerie qui à ouvert ses portes en 2015. Mélant tradition et modernité cette maison à sut rapidement devenir un des acteurs incontournables du rhum agricole martiniquais. Bête à feu est une de leur dernière création. La canne longue, coupée à la main, est acheminée au moulin à trois rolls de la distillerie A1710, située à l’Habitation du Simon au François en Martinique. Elle est broyée une seule fois afin d’en extraire son nectar. Distillé dans un alambic en cuivre muni de sa colonne à 7 plateaux, Bête à Feu est ensuite réduit lentement à 50.9 %. | I91: Nez : canne fraîche, banane, mangue, zeste de citron vert Bouche : fruits tropicaux, canne cuite, asséchante Finale : riche, minérale, longue | J91: 36.25 | K91: 0.2 | L91: =IF(K91="","",ROUND(J91*(1+K91),2)) -> 43.5 | M91: Martinique | O91: 1.3 | P91: Oui | Q91: 264 | R91: https://abcterroirs.com/index.php?id_product=264&controller=product
A92: A-03562 | C92: Ajoutée | D92: PLANTERAY RUM STIGGINS' FANCY PINEAPPLE - Boisson Spiritueuse à base de Rhum | E92: 42.9 | F92: Planteray Stiggins' Fancy Pineapple | G92: Plantation Pineapple Rhum | H92: Issu d’un processus de fabrication unique les ananas sont épluchés à la main. L’écorce du fruit est ensuite infusée avec du Plantation 3 stars (Barbade, Jamaïque, Trinidad) durant une semaine, puis le rhum distillé. Bien avant cette étape, la chair de l’ananas est infusée avec du Plantation Original Dark (Trinidad, Jamaïque) pendant plusieurs mois. Enfin, le distillat et l’infusion sont assemblés par le maitre de chai de la maison Ferrand. | I92: Nez : Ananas frais, vanille, canne à sucre Bouche : Surprenante car non sucré, ananas bien mûre, vanillé Finale : Gourmande en restant sur les sensations d'ananas, de rhum et vanille | J92: 35.75 | K92: 0.2 | L92: =IF(K92="","",ROUND(J92*(1+K92),2)) -> 42.9 | M92: Caraïbes | N92: Degré d'alcool: 40% ; Volume: 70cl | O92: 1.4 | P92: Non | Q92: 268 | R92: https://abcterroirs.com/index.php?id_product=268&controller=product
A93: A-03560 | B93: A-03560 | C93: Confirmée | D93: RHUM KARUKERA Blanc Agricole - Guadeloupe | E93: 41.5 | G93: Karukera Blanc 50% - Guadeloupe | H93: Le rhum blanc agricole Karukera est élaboré à partir du jus d'une seule variété de canne à sucre, la "Canne Bleue". Cette variété de canne tient son nom de sa cire abondante qui lui donne une couleur bleutée. Fin et puissant ce rhum s'appréciera totalement en Ti' Punch créole (citron vert et cassonnade) | J93: 34.5833 | K93: 0.2 | L93: =IF(K93="","",ROUND(J93*(1+K93),2)) -> 41.5 | M93: Rhums | N93: Degré d'alcool: 50% ; Volume: 70cl | O93: 1.5 | P93: Non | Q93: 269 | R93: https://abcterroirs.com/index.php?id_product=269&controller=product
A94: A-03559 | C94: Ajoutée | D94: RHUM KARUKERA Rhum Vieux Agricole - Guadeloupe | E94: 55.5 | G94: Karukera Rhum Vieux-Guadeloupe | H94: Ce rhum vieux a vieilli plus de 3 années en fûts ayant contenu du Cognac. Lors de l'élaboration des rhums vieux, le Maître de Chai favorise exclusivement l'expression naturelle du terroir. Aucun artifice ne vient abîmer la sélection rigoureuse effectuée par ce dernier. | I94: Nez : Cannelle, muscade, cacao Bouche : Souple et dense, marqué par les épices Finale : Suave et intense | J94: 46.25 | K94: 0.2 | L94: =IF(K94="","",ROUND(J94*(1+K94),2)) -> 55.5 | M94: Guadeloupe | N94: Degré d'alcool: 42% ; Volume: 70cl | O94: 1.5 | P94: Non | Q94: 270 | R94: https://abcterroirs.com/index.php?id_product=270&controller=product
A95: A-03508 | B95: A-03508 | C95: Confirmée | D95: RHUM LONGUETEAU LE VIEUX - Guadeloupe | E95: 49.9 | F95: LMB : « Longueteau Le Vieux » | G95: Longueteau Rhum vieux 3 ans - Guadeloupe | H95: Rhum agricole vieilli pendant 3 ans dans des fûts ayant contenu du Cognac. La famille Longueteau produit du rhum depuis 1895, de manière indépendante, un véritable "rhum de récoltants". Elle est l'unique distillerie de Guadeloupe à être autonome dans sa culture de cannes à sucre. | I95: Nez : Cannelle, muscade, cacao Bouche : Souple et dense, marqué par les épices Finale : Suave et intense | J95: 38.25 | K95: 0.2 | L95: =IF(K95="","",ROUND(J95*(1+K95),2)) -> 45.9 | M95: Rhums | N95: Degré d'alcool: 45% ; Volume: 70cl | O95: 1.4 | P95: Non | Q95: 271 | R95: https://abcterroirs.com/index.php?id_product=271&controller=product
A96: A-03662 | B96: A-03662 | C96: Confirmée | D96: RHUM COLOMA 8 ans - Colombie | E96: 43.9 | G96: Coloma 8 ans - Colombie | H96: Deux femmes sont à l’origine de ce rhum : Sandra Reategui et Judith Ramirez. Elles font partie des rares femmes à avoir pu faire leur place dans le monde encore très masculin des maîtres rhumiers, et à s’être imposées comme des références. Ce qui fait la spécificité de ce rhum, c’est qu’il est issu de la distillation de deux variétés de canne à sucre ; Vieilli 8 ans en ex-fûts de bourbon et affiné 3 mois en ex-fûts de liqueur de café. | I96: Nez : café, cacao Bouche : vanille, amande Finale : onctueuse, gourmande | J96: 36.5833 | K96: 0.2 | L96: =IF(K96="","",ROUND(J96*(1+K96),2)) -> 43.9 | M96: Rhums | N96: Degré d'alcool: 40% ; Volume: 70cl | O96: 1.9 | P96: Non | Q96: 273 | R96: https://abcterroirs.com/index.php?id_product=273&controller=product
A97: A-01533 | B97: A-01533 | C97: Confirmée | D97: RHUM BOTRAN N°18 | E97: 59.9 | G97: Botran 18 Guatemala | H97: Distillerie du Guatemala qui est situé 2300 mètres d'altitudes. Créée par la famille Botran en 1939, qui produisait au départ de l'eau-de-vie de canne à sucre. Les rhums sont réalisés à partir de miel vierge de canne qui donne des notes végétales et fruitées. ils sont vieillis dans 4 types de fûts différents : bourbon, bourbon rebrulé, Xérès et Porto. | I97: Nez : vanille - bois de santal Bouche : banane flambées - boisé Finale : épicé - longue - persistance | J97: 49.9167 | K97: 0.2 | L97: =IF(K97="","",ROUND(J97*(1+K97),2)) -> 59.9 | M97: Rhums | N97: Degré d'alcool: 40% ; Volume: 70cl | O97: 1.8 | P97: Non | Q97: 277 | R97: https://abcterroirs.com/index.php?id_product=277&controller=product
A98: A-03511 | B98: A-03511 | C98: Confirmée | D98: PUNCH LONGUETEAU - Divers parfums - Guadeloupe | E98: 39.9 | G98: Punch Longueteau – Guadeloupe | H98: Punchs aux fruits avec une macération de plusieurs semaines dans du rhum blanc. La famille Longueteau produit du rhum depuis 1895, de manière indépendante, un véritable "rhum de récoltants". Elle est l'unique distillerie de Guadeloupe à être autonome dans sa culture de cannes à sucre. | I98: Parfums disponibles : maracuja - noix de coco - schrubb | J98: 33.25 | K98: 0.2 | L98: =IF(K98="","",ROUND(J98*(1+K98),2)) -> 39.9 | M98: Rhums | N98: Degré d'alcool: 25% ; Volume: 1L | P98: Oui | Q98: 279 | R98: https://abcterroirs.com/index.php?id_product=279&controller=product
A99: A-03792 | B99: A-03792 | C99: Confirmée | D99: RHUM CHAMAREL XO PX | E99: 173.9 | G99: Chamarel PX - île Maurice | H99: Rhumerie située sur l'île Maurice dans la ville du même nom. En 1996, la famille Couacaud a acheté le domaine de l'Exil qui cultivait au départ que de la canne à sucre bleue, rouge et jaune sur 220 hectares. En 2008, ils décident de construire une distillerie pour ne produire que des rhums en pur jus de canne. | I99: Rhum pur jus de canne vieillit 6 ans en fût de chêne français avec une finition de 2 ans en fût de Xérès Pedro Ximénez. Nez : fruits secs, vanille Bouche : fruits secs, épices, vanille, figue Finale : boisée avec une belle douceur | J99: 144.9167 | K99: 0.2 | L99: =IF(K99="","",ROUND(J99*(1+K99),2)) -> 173.9 | M99: Rhums | N99: Degré d'alcool: 45% ; Volume: 70cl | O99: 2 | P99: Non | Q99: 280 | R99: https://abcterroirs.com/index.php?id_product=280&controller=product
A100: A-02278 | B100: A-02278 | C100: Confirmée | D100: RHUM CLAIRIN LE ROCHER | E100: 53.5 | G100: Rhum Clairin Le Rocher – Haïti | H100: Distillerie fondée par Romulus Bethel au centre de l'île d'Haïti, " Le Rocher" est inspiré d'un extrait de la bible. Ces rhums sont réalisés à partir d'un sirop de canne à sucre fabriqué de trois variétés de canne. Ils sont millésimés de l'année de chaque récolte. | I100: Nez : sucres caramélisés - beurre - fruits tropicaux Bouche : poivrées - fumées Finale : citronnées | J100: 44.5833 | K100: 0.2 | L100: =IF(K100="","",ROUND(J100*(1+K100),2)) -> 53.5 | M100: Rhums | N100: Degré d'alcool: 47.2% ; Volume: 70cl | O100: 1.4 | P100: Oui | Q100: 281 | R100: https://abcterroirs.com/index.php?id_product=281&controller=product
...

Sheet Descriptions HTML
A1: Référence LMB | B1: Désignation | C1: Description courte (HTML) | D1: Description longue (HTML) | E1: ID PrestaShop
A2: A-01002 | B2: Palets chocolat et fleur de sel bio – Gwenrann 85 g | C2: <p><strong>SUPERBE CHOCOLAT NOIR OU LAIT AVEC INCLUSION DE FLEUR DE SEL, LE COMPAGNON IDEAL POUR UNE PAUSE CAFÉ !</strong></p> <p><strong>MERCI LAURENT POUR CETTE CREATION QUI EST UN DES SUCCES DU MAGASIN !!</strong></p> | D2: <p>Gwenrann, Pays Blanc – ancien nom breton de la ville de Guérande. Un très fin palet de chocolat 70% de cacao au sein duquel est déposé de la fleur de sel, de Guérande bien sûr... Allergènes : traces de gluten et de fruits à coque. Création L'ATTELIER / Saint Nazaire</p> | E2: 101
A3: A-02862 | B3: Noix de cajou caramélisées et salées bio 110 g | C3: <p><strong>ATTENTION, PRODUIT ADDICTIF DU MAGASIN, NE PAS GOUTER... C'EST TROP BON ! </strong></p> <p><strong>EMBELLISSEZ VOS APÉROS AVEC CES CAJOUS SALÉES, MERCI LAURENT... OU PAS !!</strong></p> | D3: <p>La noix de cajou est un véhicule parfait pour mettre en valeur une épice, ici association noix de cajou caramélisée au fameux piment d’Espelette AOP. Le croquant de la fine couche de caramel est suivi par une imbrication d’arômes sucrés salés enveloppés par la vivacité raisonnable du piment d’Espelette. Une tuerie BIS pour l'apéro. Allergènes : traces de gluten et de fruits à coque. Création Laurent : L'ATTELIER / Saint Nazaire</p> | E3: 102
A4: A-02862 | B4: Noix de cajou caramélisées et poivre de Kampot bio 110 g | C4: <p><strong>Attention produit addictif et original pour l'apéro, le goûter c'est succomber !</strong></p> | D4: <p>La noix de cajou est un véhicule parfait pour mettre en valeur une épice donc a été associée cette noix de cajou caramélisée au poivre de Kâmpôt AOP. Le croquant de la fine couche de caramel est suivi par une combinaison d’arômes sucrés &amp; salés enveloppés par la tonicité des deux poivres rouge et noir... Une tuerie pour l'apéro. Allergènes : traces de gluten et de fruits à coque. Création Laurent LK / Saint Nazaire</p> | E4: 103
A5: A-02830 | B5: Quernons d'Ardoise – sachet 100 g (x13) | C5: <p>Les Quernons d'Ardoise, la célèbre spécialité d'Angers : une fine nougatine enrobée de chocolat bleuté, en souvenir des ardoises de l'Anjou. Sachet de 13 pièces.</p> <p>Parfait au goûter, avec un café, ou pour garnir un coffret gourmand.</p> <p>Une question ? Nos cavistes vous conseillent volontiers en boutique ou au 02 40 89 76 26.</p> | D5: <p>Spécialité angevine gourmande sur une base nougatine et chocolat.</p> | E5: 109
A6: A-01409 | B6: Petits beurres faits à Clisson (44) 70 g | C6: <p><strong>En parfum disponible : noisettes cacao / sarrasin fève de tonka / caramel salé / muroise. Très artisanal et très local, l'idéal au final ! Sachet 70g</strong></p> | D6: <p>Anne-Hélène est la fondatrice de Maison Suzanne. C’est en fait sa grand-mère Suzanne, qui l’a inspirée. Elle propose dans le vignoble nantais à côté de Clisson des biscuits gourmands confectionnés avec des matières premières de qualité. A découvrir !</p> | E6: 114
A7: A-02604 | B7: Whisky Hellyers Road – Tasmanie | D7: Incontournable de la distillerie Hellyers Road, ce single malt est produit à partir d’orge maltée locale, produite sur l’île de Tasmanie dans le sud de l’Australie. | E7: 116
A8: A-02562 | B8: LA PLAGE (Melon B) - Les Trois Toits | C8: <p><strong>Muscadet devenu un joli reflet du domaine des trois toits ! </strong></p> | D8: <p>Cette cuvée de printemps est toute en fraîcheur, sur de belles notes d'agrumes. A déguster au pied levé, en toute simplicité, en pique nique, et pourquoi pas à la plage !</p> | E8: 118
A9: A-02455 | B9: Coup de Foudre – Domaine de la Fessardière | C9: <p><strong>Un vrai coup de foudre pour ce vin, outre l'image, c'est du plaisir et la nouvelle génération de muscadet plus rond et charmeur !</strong></p> | D9: <p>La robe présente une belle couleur jaune. Le nez est plaisant, à la fois fruité et minéral sur le citron et la pêche. Ce vin est équilibré, rond avec ses notes citronnées et de fleur blanche. Frais et léger, ce muscadet élevé 9 mois dans un foudre de chêne ancien saura vous surprendre.</p> | E9: 120
A10: A-02454 | B10: La Mer, muscadet bio – Domaine de la Fessardière | C10: <p>Vin en apparence classique dans un premier temps, puis un second temps où se libèrent des notes fruitées.</p> <p>Bref, typicité du muscadet : vivacité et salinité, puis une finale plus aromatique, que du bonheur ! BIO et consigné !!</p> | D10: <p>Robe jaune pâle, nez floral et fruité, notes d’agrumes, on retrouve des parfums iodés et une touche fumée. La bouche est ronde, charnue, fruitée et acidulée.</p> | E10: 121
A11: A-02321 | B11: Rhum épicé Cinq-Cinq Spiced bio – Distiloire 70 cl | D11: <p>Rhum ambré de dégustation, le Spiced Rhum 5.5 c’est la rencontre gourmande de l’Amérique du sud et du Val de Loire autour de 5 plantes et épices. Sa double maturation de plusieurs années en fût de Bourbon puis 5 mois en fût de vin de Loire liquoreux, lui apporte caractère et élégance. Artisanal, 100% bio et naturel, sans additif ni colorant, le Spiced Rhum 5.5 est également peu sucré (seulement 20 g/L) pour une dégustation sans fausse note !</p> | E11: 122
A12: A-02256 | B12: Gin Cotswolds Dry Gin – Angleterre | C12: <p>Le Cotswolds Dry Gin est un gin artisanal anglais élaboré dans la région des Cotswolds. Distillé lentement en alambic pot still et titrant 46 %, il se distingue par l’utilisation d’une forte concentration de neuf botaniques dont genièvre, lavande locale, pamplemousse rose et zestes de citron vert frais.</p> <p>Le nez dévoile des arômes frais et épicés d’agrumes et de coriandre.</p> <p>En bouche, le genièvre et le pamplemousse s’équilibrent avec des notes florales et légèrement épicées. Riche en huiles essentielles, il devient légèrement trouble avec la glace ou le tonic, offrant un Gin &amp; Tonic intense, frais et aromatique</p> | D12: <p>Elaboré à partir d’un spiritueux à base de blé, ce gin est infusé par macération ou par vapeur avec des botaniques de provenance locale, à savoir de la région de Cotswolds au sud-ouest de l’Angleterre.</p> | E12: 123
A13: A-02254 | B13: Rhum Neisson Le Rhum (blanc) – Martinique | C13: <p>Festival de cannes fraîches ! Deux paramètres expliquent ce rhum blanc complexe : un sous-sol d’origine volcanique dont se nourrissent les cannes à sucre de La Thieubert et l’influence du littoral Caraïbe sur un climat très sec et ensoleillé. Neisson est le fruit d’un long travail de maturation, au cours duquel les crus sont brassés et aérés régulièrement.</p> | E13: 124
A14: A-02216 | B14: Whisky Armorik Classic – Bretagne | D14: <p>Pierre angulaire de la gamme, Armorik Classic est le fruit d’un vieillissement effectué en fûts de bourbon de différents âges. Doux, onctueux et gourmand, il met en évidence la qualité du vieillissement sur la côte bretonne et l’expertise de leur maître de chai.</p> | E14: 125
A15: A-02192 | B15: Coffret La Nantillaise – Grand | C15: <p><strong>Coffret sans alcool, bien représentatif de Nantes et du département en sucré salé</strong></p> | D15: <p>Assortiment sans alcool autour du Nantillais, sirop très naturel historique de Nantes. Composition sirop 47cl (plusieurs parfums) Salé : Rillette de poisson de Loire. Sucré : tablette de chocolat torréfié à Nantes. Petit clin d'œil avec le berlingot nantais, 200g, et aussi les petits beurre de la maison Suzanne, biscuit historique de la ville.</p> | E15: 126
A16: A-05222 | B16: Coffret 100 % sarrasin – Moyen | C16: <p><strong>Création originale autour du sarrasin, surnommé le blé noir, avec beaucoup de créations spécifiques au magasin. Le cidre est un gros succès du magasin avec cette jolie infusion de blé noir qui parfume fortement à l'ouverture et qui s'équilibre en bouche, les autres produits prouvent toute l'harmonie sucrée et salée que peut procurer cette plante bretonne.</strong></p> | D16: <p>Une sélection artisanale autour du Sarrasin à dominante salée. Cidre et crème de caramel viennent de Bretagne, les autres produits du département Loire-Atlantique.</p> <p>Composition : cidre Kystin au blé noir torréfié (75cl), gressins de blé noir au romarin (100g), rillettes de canard au sarrasin grillé (90g), petit beurre au sarrasin et fève de tonka (90g), crème caramel salé sarrasin (40g), tablette chocolat au sarrasin (135g)</p> | E16: 127
A17: A-02989 | B17: Pâté ou rillettes à la langouille – Labbé-Simon | C17: <p><strong>Pâtés ou rillettes de porc mélangées avec 20% de langouille. Belle création locale. Ici pot de 90g</strong></p> | D17: <p>La langouille est un produit de charcuterie artisanale. Elle est élaborée à partir de langue de porc saumurée, fumée, enveloppée dans un boyau naturel de bœuf et cuite dans un bouillon. Dans son laboratoire situé à Saint-Malo-de-Guersac, Labbe Simon en a fait sa spécialité depuis 1982.</p> | E17: 128
B18: COFFRET ASSORTIMENT MARIN SANS ALCOOL | C18: <p><b>Sélections de produits régionaux issus de la pêche de Loire ou bien de l'Atlantique. Assortiment joliment varié puisqu'on trouve une boite de sardines millésimées, tartares d'algues ou salicornes, fleur de sel de la presqu'ile de Guérande, soupe et rillettes de poissons.</b></p> | D18: <p>Rillettes de poisson de Loire - Claude Janin. Pêche traditionnelle de poissons sauvages et élaboration artisanale des recettes. 780g Soupe de poisson de l'Atlantique - Bernard Marot. Un ancien poissonnier nantais qui aujourd"hui possède sa propre conserverie en Loire Atlantique. 80g Tartare d'algues - Christine Le Tennier. Des algues bretonnes pour l'élaboration de recettes gourmandes et originales. 90g Fleur de sel de la presqu'ile de Guérande - 100g rillettes de poisson de l'Atlantique - Bernard Marot. 100g Sardines millésimées - La perles des dieux. Dessin de Delphine Cossais ou de Coralie Joulin. 115g</p> | E18: 129
A19: A-02146 | B19: Les Gralettes (fié gris) – Éric Chevalier | C19: <p><strong>Spécialiste du Fié Gris, Eric Chevalier nous offre une cuvée BIO idéale pour les cuisines asiatique ou exotiques !</strong></p> | D19: <p>Appelé aussi sauvignon rose, le cépage était présent sur le Val de Loire et le Haut-Poitou avant la crise phylloxérique, mais disparaît pratiquement au profit du sauvignon blanc, son plus proche cousin. Désormais, seuls quelques trop rares vignerons pratiquent à nouveau ce cépage afin de bénéficier de ses possibilités aromatiques.</p> | E19: 130
A20: A-02114 | B20: Coffret Nantes surprenant – Moyen | C20: <p><span style="background-color:#ffffff;"><span style="color:#666666;font-family:Roboto, sans-serif;"><span style="font-size:14px;letter-spacing:0.5px;">Sélections Nantaises mais surprenantes avec quelques-uns de nos meilleurs produits. Composition :Diablotine, apéritif composé de muscadet, de rhum et de sirop de fruit originaux (75cl). Salé : Saucisson fleur de sel local, des rillettes de poissons de Loire, fondantes en bouche, travaillée sur le filet du poisson et artisanal et des petits beurre salés artisanaux. Sucré : Des raisins secs macérés dans un muscadet vendanges tardives et enrobés de chocolat noir. Petit clin d'œil sucré avec une confiture de muroise®, fruit emblématique du vignoble nantais issu d'un hybride naturel de mûre et de framboise.</span></span></span></p> | D20: <p>Diablotine (75cl). Saucisson fleur de sel local, des rillettes de poissons de Loire Janin 100g , sablés Maison Suzanne 80g. Des raisins secs enrobés de chocolat noir 90g. Une confiture de muroise® 45g.</p> | E20: 131
A21: A-01985 | B21: Coffret 100 % Nantaises – Moyen | C21: <p><strong>Sélection de produits artisanaux sucrés salés et créés uniquement par des Femmes nantaises : Bérangère, Christine, Estelle, Magali, Sandrine, Anne-Hélène, , Aurore, Véronique, Charlotte. Best of de notre magasin très révélateur du départemetn Loire-Atlantique : muscadet, bière, biscuits, légumes, rillettes...</strong></p> | D21: <p>Composition : Rillettes de canard les délices du petit gué (80g) Tartinable de légumes Papilles et petits plats (90g) Confiture de muroise (220g) Le sablé de la tarte bauloise (180g) Petit beurre artisanal à la fleur de sel fabriqué à Clisson par Maison Suzanne (80g) ,Vin blanc " La Mer " Domaine de la Fessardière (75cl) Bière de charlotte (75cl)</p> | E21: 132
A22: A-01978 | B22: Coffret Kir nantais | C22: <p><b>Une collection "Made In Nantes" avec des spécialités typiques. Muscadet et sirop le nantillais sont associés pour former le kir 100% Nantais et accompagnés de déclinaisons salées autour du muscadet : saucisse et canard et de quelques autres typicités dont le dessert historique au rhum, le gâteau nantais.</b></p> | D22: <p>Composition : Muscadet fruité et minéral, par la maison Cormerais, idéal pour l'apéritif et les crustacés à marier avec Nantillais : sirop sans alcool qui existe depuis plus de 20 ans. Salé : rillettes de canard au muscadet par Bérangère 100g, saucisse sèche au muscadet par le petit Landréen 150g environ, fleur de sel de la presqu'ile de Guérande 100g. Sucré : sachet de Berlingots aux fruits 200g et gâteau nantais 130g</p> | E22: 133
A23: A-05447 | B23: Coffret Lulu la Nantaise | C23: <p>LULU la nantaise, elle en buvait au petit-déjeuner... de la liqueur de petit beurre ?</p> | D23: <p>Déclinaison autour du petit beurre avec des biscuits faits maison, sa boite, une liqueur au goût de biscuit ainsi qu'une pâte à tartiner.</p> <p>Composition :</p> <ul style="list-style-type:disc;"><li>Liqueur au délicieux goût de biscuit à déguster seul ou en nappage (20cl)</li> <li>Petit beurre fabriqué avec amour à Clisson (44) au bon goût de beurre frais (70g)</li> <li>Boite à l'effigie du plus célèbre petit écolier du monde</li> <li>Dessous de verre LULU</li> <li>tablette chocolat petit beurre</li> </ul> | E23: 134
A24: A-01939 | B24: Whisky Nikka From The Barrel (blend) – Japon | D24: Bouteille iconique du groupe Nikka, le From The Barrel représente à lui seul la maîtrise de l’assemblage nippon : puissance, finesse et équilibre. Bluffant à plus d’un titre, ce blend aux 100 whiskies confondrait plus d’un amateur qui ne jure que par les single malts. Ici, les fruits bien mûrs, voire confits donnent le change à des épices de caractère. Le tout faisant passer les 51,4% d’alcool (presque) comme une lettre à la poste … L’art de l’assemblage avec un grand A | E24: 136
A25: A-01936 | B25: Whisky Nikka Coffey Grain (single grain) – Japon | D25: Elaboré à partir d’une majorité de maïs provenant des alambics « Coffey », ce single grain nous offre un aperçu des whiskies de grain qui forment la base de tous les blends de la maison Nikka, au style particulièrement suave et charmeur. | E25: 137
A26: A-01927 | B26: Whisky Kornog Roc'h Hir (tourbé) – Bretagne | D26: Whisky tourbé, mais d'une grande finesse, élevé en fut de bourbon. Meilleur Whisky Européen en 2016 par Jim MURRAY Liquid Gold Award 94/100 - Whisky Bible 2020 | E26: 138
A27: A-01895 | B27: Whisky Eddu Brocéliande pur blé noir – Bretagne | C27: <p>Fondée par la famille Le Lay qui était au départ dans les années 1920 des distillateurs ambulants et en 1986 ils créèrent "La distillerie des Menhirs". La distillerie familiale commença la réalisation du whisky en 1999 avec le premier du monde uniquement de blé noir.</p> | D27: <p>Vieilli d’abord 5 ans en fût de chêne français du Limousin, EDDU Silver Brocéliande achève sa maturation en fût de chêne neuf de la forêt de Brocéliande.</p> <p>Nez : boisé - floral - fruits secs</p> <p>Bouche : boisé - vanille - fruitées</p> <p>Finale : longue et raffinée </p> | E27: 139
A28: A-01894 | B28: Whisky Eddu Ed Gwenn (single malt) – Bretagne | C28: <p>Fondée par la famille Le Lay qui était au départ dans les années 1920 des distillateurs ambulants et en 1986 ils créèrent "La distillerie des Menhirs". La distillerie familiale commença la réalisation du whisky en 1999 avec le premier du monde uniquement de blé noir.</p> | D28: <p>Obtenu par distillation d’orge uniquement, Ed Gwenn est vieilli pendant plus de 4 ans en fûts de chêne français et américain. Par analogie avec Eddu qui signifie blé noir, Ed Gwenn signifie céréale blanche en breton.</p> <p>Nez : bananes flambées - fruits exotiques mûrs</p> <p>Bouche : litchi - pêche</p> <p>Finale : douce et élégante</p> | E28: 140
A29: A-01891 | B29: Whisky Eddu Gold 10 ans – Bretagne | C29: <p>Fondée par la famille Le Lay qui était au départ dans les années 1920 des distillateurs ambulants et en 1986 ils créèrent "La distillerie des Menhirs". La distillerie familiale commença la réalisation du whisky en 1999 avec le premier du monde uniquement de blé noir.</p> | D29: <p>Whisky vieillit 10 ans en fût de chêne français</p> <p>Nez : bois de chêne torréfié - épices</p> <p>Bouche : fruits pâtissiers - miel</p> <p>Finale : fruité - épices </p> | E29: 141
A30: A-01890 | B30: Whisky Eddu Silver 100 % blé noir – Bretagne | C30: <p>Fondée par la famille Le Lay qui était au départ dans les années 1920 des distillateurs ambulants et en 1986 ils créèrent "La distillerie des Menhirs". La distillerie familiale commença la réalisation du whisky en 1999 avec le premier du monde uniquement de blé noir.</p> | D30: <p>Vieilli 5 ans en fût de chêne français ayant contenu du Cognac, EDDU Silver l’original est la première édition de la gamme EDDU.</p> <p>Nez : agrumes - fruits frais - rose - bruyère</p> <p>bouche : pomme - épice - boisé très fin </p> <p>Finale : fraîche - fruité - équilibré</p> | E30: 142
A31: A-01760 | B31: Tête de Lard (cabernet franc) – Manoir de la Tête Rouge | C31: <p>Découvrez une appellation, un terroir et un vigneron au travers de cette cuvée en BIO DYNAMIE. 100% cabernet franc. 100% racé !</p> | D31: <p>Robe rouge Grenat, note de sous bois de torréfaction légèrement animal. La bouche est soyeuse vive complexe et riche. Les tannins sont présents granuleux sans astringence. La texture est crayeuse et la final est longue. Potentiel de garde de 10 ans, à 5 ans près !</p> | E31: 143
A32: A-01759 | B32: TÊTE D'ANGE (Chenin) - Manoir Tête Rouge | C32: <p><strong>Saumur blanc en biodynamie, élégance et terroir ! Un grand vigneron ! Vin blanc agréablement polyvalent : viande blanche, fromage, apéro...</strong></p> | D32: <p>Un joli chenin sur les terroirs de craies de Saumur. Le nez est sur la fleur blanche, la maturité du chenin est intense, des notes d’agrumes arrivent en final. En bouche, beaucoup de gras fait croire à du sucre résiduel mais le vin est sec.</p> | E32: 144
A33: A-02971 | B33: Rillettes de canard – Délices du Petit Gué 180 g | C33: <p><strong>Création locale et artisanale de Bérangère vers St Nazaire. Top qualité ! 180g</strong></p> <p><strong>ici au muscadet, existe aussi au sarrasin et muroise.</strong></p> | D33: <p>Petite entreprise artisanale, LES DELICES DU PETIT GUE est située à Frossay au sud-ouest de Nantes. Bérangère valorise les matières premières locales : canards élevés dans les communes alentour, Muscadet et Gros Plant du vignoble nantais, Coteaux du Layon, Muroise de Vallet et sel de Guérande.</p> | E33: 145
A34: A-02968 | B34: Rillettes de canard – Délices du Petit Gué 100 g | C34: <p>Petite entreprise artisanale, LES DELICES DU PETIT GUE est située à Frossay au sud-ouest de Nantes. Bérangère valorise les matières premières locales : canards élevés dans les communes alentour, Muscadet et Gros Plant du vignoble nantais, Coteaux du Layon, Muroise de Vallet et sel de Guérande.</p> | E34: 146
A35: A-01739 | B35: Terrine de porc – Papilles et Petits Plats 85 g | D35: <p>« Papilles et Petits Plats » est née en 2009 grâce aux délicieuses terrines que cuisinaient ses aïeuls. Depuis, Christine concocte pour vous tous les jours des terrines, des tartinables et des chutneys. Et bien sûr, les conserves « Papilles et Petits Plats » sont des produits artisanaux, locaux, sans additifs et de grande qualité ! Produits Made In Nantes.</p> | E35: 147
A36: A-03195 | B36: Tartinables de légumes – Papilles et Petits Plats | D36: <p>« Papilles et Petits Plats » est née en 2009 grâce aux délicieuses terrines que cuisinaient ses aïeuls. Depuis, Christine concocte pour vous tous les jours des terrines, des tartinables et des chutneys. Et bien sûr, les conserves « Papilles et Petits Plats » sont des produits artisanaux, locaux, sans additifs et de grande qualité ! Produits Made In Nantes.</p> | E36: 148
A37: A-03675 | B37: RILLETTES POISSONS DE LOIRE Claude janin | D37: <p>Claude Janin, artisan pêcheur basé à St-Juline-de-Concelles, prépare des terrines et des rillettes à base des poissons qu'il a lui même pêchés, produits qui sont labellisés « poisson sauvage du bassin de la Loire », ce qui assure la traçabilité sur la date et le lieu de pêche. Parfum : brochet beurre blanc, anguilles curé nantais, silure tomate...</p> | E37: 149
A38: A-01546 | B38: RHUM HAMPDEN 8 ans - Jamaïque | D38: Ce Hampden 8 ans, digne héritier des "Stinking Rums" Jamaïcains, est un savoureux mélange de fruits mûrs, d'épices douces et de notes finement boisées. Son profil intense et ses arômes très prononcés lui confèrent un caractère authentique et naturel. | E38: 150
A39: A-01509 | B39: Quernons d'Ardoise – boîte 60 g (x8) | C39: <p>Les Quernons d'Ardoise, la célèbre spécialité d'Angers : une fine nougatine enrobée de chocolat bleuté, en souvenir des ardoises de l'Anjou. Boîte de 8 pièces, jolie à offrir.</p> <p>Parfait au goûter, avec un café, ou pour garnir un coffret gourmand.</p> <p>Une question ? Nos cavistes vous conseillent volontiers en boutique ou au 02 40 89 76 26.</p> | D39: <p>Spécialité angevine gourmande sur une base nougatine et chocolat.</p> | E39: 152
A40: A-01507 | B40: QUERNONS BOITE 245g (x32) | D40: <p>Spécialité angevine gourmande sur une base nougatine et chocolat.</p> | E40: 153
A41: A-02959 | B41: Grand PETIT BEURRE NATURE avec Message 50g | C41: <p><strong>Petit Beurre avec message : à créer sur mesure (avec anticipation), bien sûr on peut imaginer Joyeuses fêtes...</strong></p> <p><strong>Format carte postale sympathique à offrir ou pour composer un assortiment gourmand</strong></p> | D41: <p>Anne-Hélène est la fondatrice de Maison Suzanne. C’est en fait sa grand-mère Suzanne, qui l’a inspirée. Elle propose dans le vignoble nantais à côté de Clisson des biscuits gourmands confectionnés avec des matières premières de qualité. A découvrir !</p> | E41: 155
A42: A-01407 | B42: Boîte petits beurres LU – Maison Suzanne 150 g | D42: <p>Anne-Hélène est la fondatrice de Maison Suzanne. C’est en fait sa grand-mère Suzanne, qui l’a inspirée. Elle propose dans le vignoble nantais à côté de Clisson des biscuits gourmands confectionnés avec des matières premières de qualité. A découvrir !</p> | E42: 156
A43: A-01399 | B43: Perles Fines du Coing (melon) – Château du Coing | C43: <p>À servir bien frais (6-8 °C), à l'apéritif, avec des huîtres ou pour une fête. Une alternative locale au champagne.</p> <p>Une question ? Nos cavistes vous conseillent volontiers en boutique ou au 02 40 89 76 26.</p> | D43: <p>L'un des rares vins pétillants de Loire Atlantique 100% melon, le cépage du Muscadet, très riche et élégant.</p> | E43: 157
A44: A-01368 | B44: Pastis nantais La Grue Jaune (Meskad) – Distiloire 70 cl | C44: <p>Pastis Nantais et fier de l'être, joli succès également</p> | D44: <p>Médaillé d’Argent au Concours Général Agricole Paris 2020 Le Distiloire revisite la recette traditionnelle du Pastis et ses arômes typiques (anis étoilé, réglisse et herbes provençales) autour d’une sélection de plantes locales. Un mélange unique de plantes biologiques qui offre au Pastis Meskad sa richesse aromatique incomparable. Redécouvrez la fraîcheur de cette icône indémodable de l’apéritif à la française.</p> | E44: 158
A45: A-01343 | B45: ORTHOGNEISS, muscadet en Biodynamie Domaine de l'ECU | C45: <p><strong>Superbe muscadet alliant minéralité et équilibre, un grand muscadet pour redécouvrir l'appellation, par Fred Niger !</strong></p> | D45: <p>Robe Or blanc, cristalline. Nez subtil et élégant. L’attaque est souple, la bouche est complexe et tendue avec un volume imposant. Finale imposante et salivante sur le pamplemousse rose et le noyau d’amande, notes salines prononcées. Beau potentiel de garde.</p> | E45: 159
A46: A-01314 | B46: Noix de cajou caramélisées bio 100 g | D46: <p>Cette noix de cajou vient en commerce équitable du Burkina Faso, cultivée et préparée sur place. La douceur de la noix de cajou légèrement torréfiée, enrobée d’une fine couche de caramel beurre salé pour un voyage gustatif simple et raffiné. Allergènes : traces de gluten et de fruits à coque. Création Laurent : L'ATTELIER / Saint Nazaire</p> | E46: 161
A47: A-01313 | B47: NOISETTES CARAMÉLISÉES BIO 110g | D47: Une noisette italienne, de la fameuse variété Tonda e Gentile, finement caramélisée, réhaussée par une dé-cuisson du caramel au beurre de baratte breton, affinée à la fleur de sel de Guérande. Un produit aux fortes notes de noisettes torréfiées renforcées par le jeu du sucré salé du caramel. fait par Laurent et son équipe à Saint-Nazaire. | E47: 162
A48: A-01311 | B48: Nobis (syrah) – Domaine de l'Écu | D48: <p>Cuvée vinifiée pour être sur le fruit. Un vrai vin de copains à savourer à l’apéro, sur des grillades, en famille ou pas… L’essentiel étant de prendre du plaisir et de profiter du moment présent… Vin sans chichi ni tralala ; débouchez, buvez !</p> | E48: 163
A49: A-01300 | B49: Muscadet en biodynamie – Domaine de la Pépière | C49: <p><strong>Bel équilibre pour ce muscadet travaillé ne biodynamie !</strong></p> | D49: <p>Un muscadet qui propose un nez fin, sur des notes fruitées et de pierre humide. En bouche, une attaque citronnée suivie d'une belle rondeur qui donne de l'amplitude et finissant sur une note tonique. Un compagnon idéal pour l'apéritif ou les repas autour des fruits de mer.</p> | E49: 165
A50: A-01299 | B50: Muscadet « Original » – Domaine Brégeon | C50: <p><strong>Muscadet au style intermédiaire, minéral et finesse, un très joli passe partout BIO !</strong></p> | D50: <p>Muscadet issu des terroirs de Gabbro de la commune de Gorges. A la fois solaire et salivant, il peut se garder quelques années en cave pour révéler tout son potentiel.</p> | E50: 166
A51: A-01248 | B51: Méphisto (cabernet franc en amphore) – Domaine de l'Écu | C51: <p>100% cabernet franc en BIODYNAMIE, vieilli en amphore, élu meilleur vin rouge de la Loire par le RVF il y a peu !</p> <p>Tout un programme pour un vin Nantais et un vigneron, Fred Niger, à découvrir...</p> | D51: <p>Un vin vinifié pour sublimer et respecter le Cabernet Franc, une certaine idée de la finesse et de la délicatesse, point de sur-extraction dans cette bouteille.</p> | E51: 168
A52: A-01235 | B52: Mathilde (sauvignon) – Domaine du Haut Planty | C52: <p><strong>Mathilde est revenue et est toujours là pour les afficionados de vin blanc sec mais fruité !</strong></p> | D52: <p>Assemblage flatteur de Sauvignon blanc et Sauvignon gris, ce vin accompagnera parfaitement les apéritifs et les repas mettant en valeur les produits de la mer.</p> | E52: 169
A53: A-01221 | B53: Malvoisie demi-sec bio – Domaine Landron Chartier | C53: <p><strong>Malvoisie BIO sec tendre rempli de tendresse, salinité et sucrosité réunie !</strong></p> | D53: <p>Ce cépage typique de la Méditerranée est ici un cousin du pinot gris, qui se révèle à son avantage en apéro, foie gras, voire cuisine exotique ou asiatique.</p> | E53: 170
A54: A-01124 | B54: LES CLEFS (gamay) - Landron Chartier | C54: <p>Gamay, BIO, local et puissant ! Benoit Landron sublime le gamay d'Ancenis, un exemple ici</p> | D54: <p>Une cuvée atypique de Gamay du domaine Landron-Chartier : concentré, complexe, puissant. A boire sur de belles viandes rouges, ou à garder sur 10 ans</p> | E54: 171
A55: A-01078 | B55: La Pièce de l'Orée (pinot noir) – Éric Chevalier | C55: <p><strong>100% pinot noir local et Bio ! Eric Chevalier maitrise son sujet et propose une cuvée pour le plaisir d'un début de repas, le plaisir d'un accord sur du poisson ou de la viande blanche</strong></p> <p></p> | D55: <p>Cuvée de pinot noir sur les Côtes de Grand Lieu (44) qui sera vous ravir par sa finesse et son fruité intense</p> | E55: 172
A56: A-01068 | B56: Muscadet La Grue Jaune – Éric Chevalier | C56: <p><strong>Anciennement le clos de la butte, la Grue jaune s'est imposée en cuvée référente et joliment clin d'oeil au passé industriel nantais.</strong></p> | D56: <p>Une cuvée gourmande et ronde, qui garde beaucoup de fraîcheur. BIO par Eric Chevalier</p> | E56: 173
A57: A-01003 | B57: Gwin Evan (melon de Bourgogne) – Domaine du Haut Planty | C57: <p><strong>Belle redécouverte d'un vin issu du terroir du Muscadet qui vous donnera de jolies surprises, mais pas trop. Nature !</strong></p> | D57: <p>Du Melon de Bourgogne sans soufre ajouté, plein de rondeur et de fruité, mais allégé en acidité. Du pur plaisir !</p> | E57: 174
A58: A-01002 | B58: Chocolat au lait et fleur de sel bio – Gwenrann 85 g | D58: Gwenrann, ancien nom breton de la ville de Guérande, est le nom de la première spécialité que créée par laurent et son équipe en s'installant au cœur des marais salants de Guérande. Un procédé longuement mis au point nous permet de vous faire déguster un très fin palet de chocolat 70% de cacao au sein duquel nous déposons de la fleur de sel, de Guérande bien sûr. Allergènes : traces de gluten et de fruits à coque. Création L'ATTELIER / Saint Nazaire | E58: 175
A59: A-00959 | B59: Gin nantais 1924 – Distiloire 70 cl | C59: <p>Gin Nantais et bon, bien équilibré, un vrai succès</p> | D59: <p>Médaillé d’Or au Concours Général Agricole Paris 2020 Médaillé de Bronze à l’International Spirits Challenge Londres 2019 Elaboré dans la tradition du London Dry Gin anglais, le Gin 1924 est un alcool de blé biologique redistillé en présence d’une sélection unique de 8 plantes. Construit autour des baies de genièvre et de la coriandre, la trame aromatique du Gin est ici enrichie de notes florales et légèrement épicées. Cultivées en biodynamie dans le val de Loire, la camomille et l’angélique apportent élégance et structure à l’ensemble.</p> | E59: 176
A60: A-00958 | B60: Gin Heol An Oriant bio – Gorvello 70 cl | C60: <p>17 botaniques ! Pour base des baies de genièvre et des graines de coriandre auxquelles ont été associées des épices et aromates lointaines (cardamome, poivre de cubèbe, cannelle de Ceylan, noix de muscade…), des plantes et fleurs traditionnellement employées dans la pharmacopée bretonne (réglisse, angélique, sureau…) ainsi que des zestes de citron, d’orange amère et un soupçon de gingembre frais.</p> | E60: 177
A61: A-00883 | B61: FOLLE BLANCHE LA PART DU COLIBRI | C61: <p><strong>Redécouvrez les jolies vertus du Gros Plant au travers du travail BIO des Caillé</strong></p> | D61: <p>Vin de couleur pâle à reflet vert typique du cépage dont il est issu : la folle blanche. Frais et nerveux, il dévoile également des notes minérales.</p> | E61: 178
A62: A-00624 | B62: Clisson – Domaine des Cognettes | C62: <p><strong>Cru communal très réputé, des muscadets travaillés différemment pour plus s'apparenter naturellement à des vins de Bourgogne</strong></p> | D62: <p>Belle robe limpide jaune claire aux reflets dorés. Un nez riche et complexe mêlant à la fois des fruits jaunes mûrs et des notes lactées, beurrées et légèrement citronnées. Une bouche onctueuse et structurée avec une finale tendue et très longue.</p> | E62: 182
A63: A-00566 | B63: Chardonnay « Les 3 Bois » – Éric Chevalier | C63: <p><strong>Eric Chevalier met en valeur par une belle minéralité et un bel équilibre ce chardonnay, travaillé en bio, version 100% locale en final</strong></p> | D63: <p>Simplicité et éclat du cépage chardonnay sur nos sols légers et géographie maritime.</p> | E63: 183
A64: A-00557 | B64: Champagne brut Pure Meunier – Moutardier | C64: <p><strong>Superbe champagne de vignerons indépendants sur une base 100% Pinot Meunier pour une expression pure et minérale, très joliment à l'ancienne !</strong></p> | D64: <p>Ce vin de pure origine est un Champagne pour amateurs passionnés et découvreurs de vins inédits. Insolite, la Cuvée Pure Meunier allie fraîcheur, minéralité, fruité et tendresse. Un Champagne épuré et harmonieux qui s’offre dans sa plénitude.</p> | E64: 184
A65: A-00555 | B65: Champagne brut Carte d'Or – Moutardier | C65: <p><strong>Champagne de récoltant sur une base de cépages : 80% Meunier - 15% Chardonnay - 5% Pinot Noir, qui donne une cuvée pleine de finesse et d'équilibre en bouche. Valeur plus que sûre !</strong></p> | D65: <p>Le Champagne d’apéritif, du partage en toute simplicité. La générosité, l’ampleur et la fraîcheur sont ses attributs majeurs. Crustacés et agrumes en galette de blé noir : un contraste apporté par une certaine maturité fruitée du vin.</p> | E65: 185
A66: A-00533 | B66: Carpe Diem (melon en amphore) – Domaine de l'Écu | C66: <p><strong>Vin de gastronomie, vieilli en amphores et travaillé en biodynamie pour une expression surréaliste de ce cépage phare Nantais, à accommoder "tout simplement" sur du homard, st jacques ou pintade.</strong></p> | D66: <p>Un vin vinifié 15 mois en amphores qui montre une nouvelle expression du Melon de Bourgogne</p> | E66: 186
A67: A-00496 | B67: CABERNET COT Bonnet Huteau | C67: <p><strong>Travail en biodynamie dans le pays Nantais pour un vin rouge qui offrira un bel équilibre et une puissance maitrisée. Domaine Bonnet Huteau.</strong></p> | D67: <p>Cet emballage de deux cépages possède des arômes de fruits rouges et d’épices fraîches. C’est un vin à la fois souple et bien équilibré.</p> | E67: 187
A68: A-00419 | B68: BILLES DE ROCHE ROUGE (cabernet) Melaric | C68: <p><strong>Superbe micro appellation à découvrir Puy Notre Dame, joli contresens aux saumurs rouges classiques et légers, ici vin puissamment surprenant à 14° en Bio</strong></p> | D68: <p>Un Cabernet franc généreux, alliant un nez frais à une bouche puissante et expressive. Ce vin offre aussi un beau potentiel de garde</p> | E68: 193
A69: A-00314 | B69: Atmosphères (folle blanche, pinot noir, chardonnay) – Jo Landron | C69: <p><strong>Bulles locales sur assemblage de trois cépages : folle blanche, pinot noir et chardonnay. Très bien équilibrée et légèrement fruitée. par Jo LANDRON</strong></p> | D69: <p>Nez frais, floral et fruité (groseille, poire). Bouche vive, rafraichissante aux notes de coing et légèrement briochée, avec une finale tranchante d'une pureté cristalline.</p> | E69: 195
A70: A-00292 | B70: Amphibolite, muscadet – Jo Landron | C70: <p><b>Muscadet parmi les plus réputés, travaillé en biodynamie. Plus que parfait sur huitres et fruits de mer. Par Jo Landron, une des références en local, surnommé l'Astérix du vignoble pour tout son travail de valorisation de l'appellation.</b></p> | D70: <p>Vin avec une belle spontanéité d’arôme : agrume et salinité en fin de bouche. Ici, le vin a choisi l’expression de la jeunesse.</p> | E70: 198
A71: A-00289 | B71: Amandes caramélisées bio 110 g | C71: <p><strong>Création gourmande faites à Saint Nazaire, bien équilibrée sur son caramélisé. Bio de surcroit.</strong></p> | D71: <p>Laurent a créé ici une amande italienne, finement caramélisée, rehaussée par une dé-cuisson du caramel au beurre de baratte breton, affinée à la fleur de sel de Guérande. Un produit simple et raffiné à la fois. Allergènes : traces de gluten et de fruits à coque. Produit à Saint Nazaire</p> | E71: 199
A72: A-00275 | B72: Abouriou Ancre (cuve) – Domaine du Haut Planty | C72: <p><strong>Cépage typique à découvrir, autrefois vin de soif des vignerons, il s'exprimera sur sa fraicheur et des notes fruits noirs confits et légèrement épicées. Vin naturel, naturellement bon !</strong></p> | D72: <p>Cépage modeste et rustique issu du sud-ouest. Cette jeune vigne offre une vendange très saine, vinifié en macération carbonique pendant 8 à 10 jours. La couleur et les tannins sont vite au rendez-vous. Le pressurage réalisé, les jus fermentent en cuve souterraine, la mise en bouteilles se fera 12 à 15 mois plus tard, sans soufre ajouté.</p> | E72: 200
... A77: A-01411 | B77: Petite boîte Petit Écolier LU avec petits beurres | C77: <p><strong>Très jolie boite à savon ici avec des petits beurres artisanaux faits à côté de Clisson</strong></p> | D77: <p>Sachet de 4 petits beurres faits par Anne-Hélène à la fleur de sel de Guérande (40g)</p><p>Boite à savon : 9.5 x 6 x2.7cm</p> | E77: 238
B78: Boîte Tour LU plate avec petits beurres | C78: <p><strong>Boite plate et en relief sur la tour LU avec des petits beurres artisanaux et très gourmands faits vers Clisson par Anne-Hélène, format spécial qui plait beaucoup en magasins. Le vrai petit beurre artisanal et local !</strong></p> | D78: <p>Composition : petits beurres à la fleur de sel de Guérande 150g</p> | E78: 239
A79: A-00022 | B79: Boîte sucrette Tour LU garnie – Petite | C79: <p><b>Jolie petite boite contenant un sachet de berlingots nantais et un sachet de petits beurres à la fleur de sel faits vers Clisson. Simple mais efficace avec aussi une boite qui va rester en trace du cadeau. Petits beurres personnalisables via un texte ou logo (surcoût à voir)</b></p> | D79: <p>Composition : berlingots nantais de 100g et un sachet de petits beurres à la fleur de sel 28g.</p> | E79: 240
A80: A-02825 | B80: Boîte sucrette Tour LU garnie – Grande | C80: <p><b>Assortiment de spécialités illustrant Nantes et ses gourmandises, idéal pour des cadeaux pour événements (salons...). Boite LU avec couvercle en relief et notamment des petits beurres artisanaux à l'intérieur. Petits beurres qui peuvent être personnalisés à la demande (surcoût à voir)</b></p> | D80: <p>Petite et jolie boite avec visuel Tour LU contenant un sachet de berlingots nantais 100g, des petits beurres à la fleur de sel très gourmands 28g, un sachet de fleur de sel 50g de la presqu'ile de Guérande, un pot de crème de caramel salé 50g et une sardine au chocolat au lait avec éclat de crêpe dentelle. Cette composition reste un exemple, n'hésitez pas à nous contacter...</p> | E80: 241
A81: A-01975 | B81: Coffret Folie foie gras | C81: <p><strong>Délectations autour d'un foie gras de canard entier d'origine Bretonne à la fine de Bretagne et fleur de sel de Guérande qui s'exprimera à la perfection sur des toasts 100% blé noir et d'un confit d'oignons bio local. Nous le proposons avec une bouteille demi sec typique et rare de malvoisie, en bio, fait vers Ancenis, avec un petit accompagnement délicat de raisins chocolatés macérés dans du muscadet issu de vendanges tardives.</strong></p> | D81: <p>Composition : foie gras de canard entier d'origine Bretonne à la fine de Bretagne et fleur de sel de Guérande 120g, toasts multi-graines 100% blé noir, confit d'oignons bio 90g, malvoisie bio 75cl, raisins chocolatés macérés dans du muscadet issu de vendanges tardives 80g.</p> | E81: 242
A82: A-04170 | B82: Coffret Voyage extraordinaire – Moyen | C82: <p><strong>Belle sélection Nantaise autour d'un muscadet Bio typé Jules Verne par ses jolies étiquettes (trois créations).</strong></p> | D82: <p>Muscadet 75cl bio par la famille Lieaubeau, bien équilibré, légèrement fruité. Bière de la brasserie Nautille à Rezé 75cl. Raisins chocolats macérés dans du muscadet vendanges tardives (création du magasin) sachet de 90g. Noix de cajou caramélisées au poivre de Kampot, Petit pâté à la Langouille 90g, la Langouille existe depuis 30 ans dans le département c'est une spécialité de langues de porc. Sablés apéritif de Vincent pour le clin d'œil à notre fromage local le curé nantais.</p> <p>Sur la photo, il y a les rillettes de poissons de Loire 100g de Claude Janin, mais Claude prend sa retraite, elles sont remplacées par les rillettes de poissons d'Arnaud Guéret pêcheur à Varades, possiblement avec de la Lamproie au malvoisie, hyper intéressante en texture et gout !</p> | E82: 243
A83: A-04066 | B83: Rhum Barbancourt 4 ans Trois étoiles - Haïti | C83: <p><span style="color:#545454;font-family:'Avenir LT Std', Arial, sans-serif, 'Apple Color Emoji', 'Segoe UI Emoji', 'Segoe UI Symbol';font-size:16px;text-align:justify;">La distilleries Barbancourt produit des rhums pur jus de canne à sucre, de fait il est un rhum agricole.</span></p> <p style="text-align:justify;"><span style="color:#545454;font-family:'Avenir LT Std', Arial, sans-serif, 'Apple Color Emoji', 'Segoe UI Emoji', 'Segoe UI Symbol';"><span style="font-size:16px;">Il prouve tout l'immense savoir-faire de l'emblématique distillerie fondée en 1862.</span></span></p> <p style="text-align:justify;"><span style="color:#545454;font-family:'Avenir LT Std', Arial, sans-serif, 'Apple Color Emoji', 'Segoe UI Emoji', 'Segoe UI Symbol';"><span style="font-size:16px;"></span></span></p> <p style="text-align:justify;"><span style="color:#545454;font-family:'Avenir LT Std', Arial, sans-serif, 'Apple Color Emoji', 'Segoe UI Emoji', 'Segoe UI Symbol';"><span style="font-size:16px;">Nez : léger et frais sur des notes d'épices, de vanille et de caramel craquant</span></span><span style="color:#545454;font-family:'Avenir LT Std', Arial, sans-serif, 'Apple Color Emoji', 'Segoe UI Emoji', 'Segoe UI Symbol';"><span style="font-size:16px;"></span></span></p> <p style="text-align:justify;"><span style="color:#545454;font-family:'Avenir LT Std', Arial, sans-serif, 'Apple Color Emoji', 'Segoe UI Emoji', 'Segoe UI Symbol';"><span style="font-size:16px;">Bouche : légère et vive avec des arômes de chêne, de vanille, de beurre et d'épices</span></span><span style="color:#545454;font-family:'Avenir LT Std', Arial, sans-serif, 'Apple Color Emoji', 'Segoe UI Emoji', 'Segoe UI Symbol';"><span style="font-size:16px;"></span></span></p> <p style="text-align:justify;"><span style="color:#545454;font-family:'Avenir LT Std', Arial, sans-serif, 'Apple Color Emoji', 'Segoe UI Emoji', 'Segoe UI Symbol';"><span style="color:#545454;font-family:'Avenir LT Std', Arial, sans-serif, 'Apple Color Emoji', 'Segoe UI Emoji', 'Segoe UI Symbol';"><span style="font-size:16px;"></span></span></span></p> <p style="text-align:justify;"><span style="color:#545454;font-family:'Avenir LT Std', Arial, sans-serif, 'Apple Color Emoji', 'Segoe UI Emoji', 'Segoe UI Symbol';"><span style="font-size:16px;">Finale : douce</span></span></p> | D83: <p style="text-align:justify;"></p> <p style="text-align:justify;"></p> | E83: 244
A84: A-01555 | B84: Rhum Plantation Gran Añejo – Guatemala | C84: <p><span style="color:#333333;font-family:FuturaPTBook, 'system-ui', '-apple-system', BlinkMacSystemFont, 'Segoe UI', Roboto, Ubuntu, 'Helvetica Neue', sans-serif;font-size:15px;">Plantation Rum Gran Anejo provient de l'assemblage de différents rhums du Guatemala, âgés entre 3 et 4 ans, vieillis en fûts de bourbon dans les Caraïbes, puis affinés dans de vieux fûts de chêne français au Château de Bonbonnet. Très riche, il est marqué par des notes d'agrumes confits et de raisins secs, de pivoine, de fruit de la passion et d'épices.</span></p> | E84: 245
A85: A-04087 | B85: Rhum Fontanel blanc – Rhumerie du Vignoble | C85: <p>Produit au cœur du vignoble nantais ce rhum 100% artisanal, à Saint Fiacre sur Maine, à base de mélasse de canne à sucre Bio du Paraguay. Tout y est fait sur place, fermentations, distillations et embouteillage.</p> <p>Il saura vous séduire avec ses parfums de cannes cuites et son onctuosité. Le parfait compagnon pour vos ti 'punchs ou cocktails.</p> | E85: 258
A86: A-04088 | B86: Rhum Fontanel Spiced – Rhumerie du Vignoble | C86: <p>Produit au cœur du vignoble nantais ce rhum 100% artisanal, à Saint Fiacre sur Maine, à base de mélasse de canne à sucre Bio du Paraguay. Tout y est fait sur place, fermentations, distillations et embouteillage.</p> <p>Affiné dans d'ancien fûts de Sherry, avec une macération d'épices gourmandes. Vanille, cannelle, muscade, poivre, clous de girofle et caramel. Aucune épices ne vient en écraser une autre. Le résultat est flatteur avec cette sensation de caramel mou vanillé mais sans tombé dans l'excès de sucre.</p> | E86: 259
A87: A-03506 | B87: RHUM SOL TARASCO 8 ANS - Mexique | C87: <p>Sol Tarasco est produit à partir de jus de canne à sucre locale mexicaine AOC, ce qui en fait un rhum agricole. Elles poussent sur un sol rouge volcanique à de plus de 1 270 mètres d’altitude. Une fois distillé, il est vieilli dans d'anciens fûts de bourbons et de sherry.</p> <p>Les parfums sont suaves, vanillés et les parfums de canne sont mis en valeur. En bouche, c'est une explosion de saveurs. Bois grillé, vanillé, compoté de mangue tout en ayant une texture fraîche.</p> | E87: 260
A88: A-01531 | B88: Rhum Barbancourt 8 ans Réserve Spéciale - Haïti | C88: <p><span style="color:#545454;font-family:'Avenir LT Std', Arial, sans-serif, 'Apple Color Emoji', 'Segoe UI Emoji', 'Segoe UI Symbol';font-size:16px;text-align:justify;">La distilleries Barbancourt produit des rhums pur jus de canne à sucre, de fait il est un rhum agricole.</span></p> <p><span style="color:#545454;font-family:'Avenir LT Std', Arial, sans-serif, 'Apple Color Emoji', 'Segoe UI Emoji', 'Segoe UI Symbol';font-size:16px;text-align:justify;"></span></p> <p style="text-align:justify;"><span style="color:#545454;font-family:'Avenir LT Std', Arial, sans-serif, 'Apple Color Emoji', 'Segoe UI Emoji', 'Segoe UI Symbol';"><span style="font-size:16px;">Nez : vanillé, poivré</span></span></p> <p style="text-align:justify;"><span style="color:#545454;font-family:'Avenir LT Std', Arial, sans-serif, 'Apple Color Emoji', 'Segoe UI Emoji', 'Segoe UI Symbol';"><span style="font-size:16px;">Bouche : puissante, notes torréfiées, fruits cuits (pruneaux), marmelade</span></span></p> <p style="text-align:justify;"><span style="color:#545454;font-family:'Avenir LT Std', Arial, sans-serif, 'Apple Color Emoji', 'Segoe UI Emoji', 'Segoe UI Symbol';"><span style="font-size:16px;">Finale : intense</span></span></p> <p></p> <p style="text-align:justify;"><span style="color:#545454;font-family:'Avenir LT Std', Arial, sans-serif, 'Apple Color Emoji', 'Segoe UI Emoji', 'Segoe UI Symbol';"><span style="font-size:16px;">Il prouve tout l'immense savoir-faire de l'emblématique distillerie fondée en 1862.</span></span></p> | E88: 261
A89: A-03902 | B89: RHUM MONTEBELLO 3 ANS | C89: <p>Initialement appeler "Carrière" la distillerie créée en 1930 fut racheté par la famille Marsolle en 1968, ils décident alors de la moderniser et de relancer la production. Montebello a la spécificité de placer les fûts de chêne dans des conteneurs métalliques pour accélérer le processus de vieillissement, alors que d'autres distilleries cherchent à réduire la part des anges.</p> <p>Nez : gourmand, pâtissier, vanille douce</p> <p>Bouche : canne à sucre, mangue verte, chêne grillé</p> <p>Finale : longue, gourmande, fruits confits</p> | D89: <p>Comme tous les rhums de la distillerie Montebello, il est vieilli en fûts de chêne. Le rhum 3 ans d'âge est le seul assemblage de la gamme. Il contient 3 ans d'âge (70%), 8 ans d'âge (20%) et 12 ans d'âge (10%), ce qui fait une moyenne de près de 5 ans d'âge, mais la législation oblige à ne mentionner que l'âge le plus jeune sur l'étiquette.</p> | E89: 262
A90: A-03903 | B90: RHUM MONTEBELLO 8 ANS | C90: <p>Initialement appeler "Carrière" la distillerie créée en 1930 fut racheté par la famille Marsolle en 1968, ils décident alors de la moderniser et de relancer la production. Montebello a la spécificité de placer les fûts de chêne dans des conteneurs métalliques pour accélérer le processus de vieillissement, alors que d'autres distilleries cherchent à réduire la part des anges.</p> <p>Nez : intense, pâtissier</p> <p>Bouche : canne à sucre toasté, épices, fruits secs</p> <p>Finale : longue, riche, banane flambé</p> | D90: <p>La qualité de ce rhum très vieux Montebello 6 ans est obtenue par un vieillissement en fûts de chêne américain de 180 litres ayant contenus du bourbon.</p> <p></p> | E90: 263
A91: A-03658 | B91: Rhum Bête à Feu – A1710 | C91: <p>A 1710 est une jeune distillerie qui à ouvert ses portes en 2015. Mélant tradition et modernité cette maison à sut rapidement devenir un des acteurs incontournables du rhum agricole martiniquais. Bête à feu est une de leur dernière création.</p> <p>La canne longue, coupée à la main, est acheminée au moulin à trois rolls de la distillerie A1710, située à l’Habitation du Simon au François en Martinique. Elle est broyée une seule fois afin d’en extraire son nectar.</p> <p>Distillé dans un alambic en cuivre muni de sa colonne à 7 plateaux, Bête à Feu est ensuite réduit lentement à 50.9 %.</p> <p></p> | D91: <p>Nez : canne fraîche, banane, mangue, zeste de citron vert</p> <p>Bouche : fruits tropicaux, canne cuite, asséchante</p> <p>Finale : riche, minérale, longue</p> | E91: 264
A92: A-03562 | B92: Plantation Pineapple Rhum | C92: <p style="text-align:justify;"><span style="font-family:Helvetica;font-size:15px;background-color:#f9f9f9;">Issu d’un processus de fabrication unique les ananas sont épluchés à la main. L’écorce du fruit est ensuite infusée avec du Plantation 3 stars (Barbade, Jamaïque, Trinidad) durant une semaine, puis le rhum distillé. Bien avant cette étape, la chair de l’ananas est infusée avec du Plantation Original Dark (Trinidad, Jamaïque) pendant plusieurs mois. Enfin, le distillat et l’infusion sont assemblés par le maitre de chai de la maison Ferrand.</span></p> | D92: <p>Nez : Ananas frais, vanille, canne à sucre</p> <p>Bouche : Surprenante car non sucré, ananas bien mûre, vanillé</p> <p>Finale : Gourmande en restant sur les sensations d'ananas, de rhum et vanille</p> | E92: 268
A93: A-03560 | B93: Karukera Blanc 50% - Guadeloupe | C93: <p><span style="color:#252525;font-family:Montserrat, sans-serif;"><span style="font-size:16px;">Le rhum blanc agricole Karukera est élaboré à partir du jus d'une seule variété de canne à sucre, la "Canne Bleue". Cette variété de canne tient son nom de sa cire abondante qui lui donne une couleur bleutée. </span></span></p> <p><span style="color:#252525;font-family:Montserrat, sans-serif;"><span style="font-size:16px;">Fin et puissant ce rhum s'appréciera totalement en Ti' Punch créole (citron vert et cassonnade) </span></span></p> | E93: 269
A94: A-03559 | B94: Karukera Rhum Vieux-Guadeloupe | C94: <p style="text-align:justify;">Ce rhum vieux a vieilli plus de 3 années en fûts ayant contenu du Cognac. Lors de l'élaboration des rhums vieux, le Maître de Chai favorise exclusivement l'expression naturelle du terroir. Aucun artifice ne vient abîmer la sélection rigoureuse effectuée par ce dernier.</p> | D94: <p>Nez : Cannelle, muscade, cacao</p> <p>Bouche : Souple et dense, marqué par les épices</p> <p>Finale : Suave et intense</p> | E94: 270
A95: A-03508 | B95: Longueteau Rhum vieux 3 ans - Guadeloupe | C95: <p style="text-align:justify;">Rhum agricole vieilli pendant 3 ans dans des fûts ayant contenu du Cognac. </p> <p style="text-align:justify;">La famille Longueteau produit du rhum depuis 1895, de manière indépendante, un véritable "rhum de récoltants". Elle est l'unique distillerie de Guadeloupe à être autonome dans sa culture de cannes à sucre.</p> | D95: <p style="text-align:justify;">Nez : Cannelle, muscade, cacao</p> <p style="text-align:justify;">Bouche : Souple et dense, marqué par les épices</p> <p style="text-align:justify;">Finale : Suave et intense</p> | E95: 271
A96: A-03662 | B96: Coloma 8 ans - Colombie | C96: <p style="text-align:justify;">Deux femmes sont à l’origine de ce rhum : Sandra Reategui et Judith Ramirez. Elles font partie des rares femmes à avoir pu faire leur place dans le monde encore très masculin des maîtres rhumiers, et à s’être imposées comme des références.</p> <p style="text-align:justify;">Ce qui fait la spécificité de ce rhum, c’est qu’il est issu de la distillation de deux variétés de canne à sucre ; Vieilli 8 ans en ex-fûts de bourbon et affiné 3 mois en ex-fûts de liqueur de café.</p> | D96: <p>Nez : café, cacao</p> <p>Bouche : vanille, amande</p> <p>Finale : onctueuse, gourmande</p> | E96: 273
A97: A-01533 | B97: Botran 18 Guatemala | C97: <p>Distillerie du Guatemala qui est situé 2300 mètres d'altitudes. Créée par la famille Botran en 1939, qui produisait au départ de l'eau-de-vie de canne à sucre. Les rhums sont réalisés à partir de miel vierge de canne qui donne des notes végétales et fruitées. ils sont vieillis dans 4 types de fûts différents : bourbon, bourbon rebrulé, Xérès et Porto. </p> | D97: <p>Nez : vanille - bois de santal</p> <p>Bouche : banane flambées - boisé</p> <p>Finale : épicé - longue - persistance</p> | E97: 277
A98: A-03511 | B98: Punch Longueteau – Guadeloupe | C98: <p><span style="text-align:justify;">Punchs aux fruits avec une macération de plusieurs semaines dans du rhum blanc.</span></p> <p><span style="text-align:justify;"></span></p> <p><span style="text-align:justify;">La famille Longueteau produit du rhum depuis 1895, de manière indépendante, un véritable "rhum de récoltants". Elle est l'unique distillerie de Guadeloupe à être autonome dans sa culture de cannes à sucre.</span></p> | D98: <p>Parfums disponibles : maracuja - noix de coco - schrubb</p> | E98: 279
A99: A-03792 | B99: Chamarel PX - île Maurice | C99: <p>Rhumerie située sur l'île Maurice dans la ville du même nom. En 1996, la famille Couacaud a acheté le domaine de l'Exil qui cultivait au départ que de la canne à sucre bleue, rouge et jaune sur 220 hectares. En 2008, ils décident de construire une distillerie pour ne produire que des rhums en pur jus de canne.</p> | D99: <p>Rhum pur jus de canne vieillit 6 ans en fût de chêne français avec une finition de 2 ans en fût de Xérès Pedro Ximénez.</p> <p>Nez : fruits secs, vanille</p> <p>Bouche : fruits secs, épices, vanille, figue</p> <p>Finale : boisée avec une belle douceur </p> <p></p> | E99: 280
A100: A-02278 | B100: Rhum Clairin Le Rocher – Haïti | C100: <p>Distillerie fondée par Romulus Bethel au centre de l'île d'Haïti, " Le Rocher" est inspiré d'un extrait de la bible. Ces rhums sont réalisés à partir d'un sirop de canne à sucre fabriqué de trois variétés de canne. Ils sont millésimés de l'année de chaque récolte. </p> | D100: <p>Nez : sucres caramélisés - beurre - fruits tropicaux</p> <p>Bouche : poivrées - fumées</p> <p>Finale : citronnées </p> <p></p> | E100: 281
A101: A-03790 | B101: La Favorite La Flibuste 2000 Martinique | E101: 283
A102: A-01788 | B102: Pondicherry – Gorvello | C102: <p>Pondicherry, une boisson <strong>sans alcool</strong> signée Gorvello, en bouteille de 20 cl.</p> <p>À servir bien frais, à l'apéritif ou en cocktail sans alcool.</p> <p>Une question ? Nos cavistes vous conseillent volontiers en boutique ou au 02 40 89 76 26.</p> | E102: 286
B103: ORI'GIN La Piautre - Maine et Loire | C103: <p>Comme autrefois, ce Gin est préparé à partir d'une bière pur malt. Cela commence par des céréales bio (blé, orge et seigle) cultivées en Anjou puis maltées et brassées à la fabrique. Après fermentation, une double distillation au feu de bois donne une eau de vie dans laquelle vont macérer genièvre et botaniques qui va être redistillée Le cœur de chauffe obtenu est alors réduit doucement à l'eau pure et ramené à 49 degrés d'alcool. 49, comme son terroir angevin.</p> <p></p> | D103: <p>Nez : végétal, résineux, genièvre</p> <p>Bouche : épicée, coriandre, gingembre</p> <p>Finale : herbacé, gingembre</p> | E103: 290
A104: A-03535 | B104: GIN KNIFEMAKER - Haute-Garonne | C104: <p>L'histoire de Straw Bale est née avec le projet un peu fou de Gilles Victor, coutelier reconnu pendant plus de 15 ans et passionné par le Gin.</p> <p>Il ne lui en faudra pas plus pour le convaincre de faire de cette passion son nouveau métier </p> <p>Five O'clock est un gin résolument gourmand, qui met en valeur les fruits rouges.</p> <p>Nez : Fruits rouges</p> <p>Bouche : Onctueuse, cassis</p> <p>Finale : intense, fraîche</p> | E104: 292
...
